{"EventName":"StartSession","TimestampUTC":1730546273.763000,"RecordId":0,"ProjectName":"Kukoverova_Veronika","ProjectID":"00000000000000000000000000000000","Session_ID":"{46A4D377-43C5-81E5-72CD-958C72118432}","Session_Label":"","Session_StartUTC":1730546273.763,"Build_Configuration":"Development","Build_IsInternalBuild":false,"Build_IsPerforceBuild":false,"Build_IsPromotedBuild":true,"Build_BranchName":"++ue5+release-5.4","Build_Changelist":35576357,"Hardware_Platform":"Windows","Hardware_GPU":"","Hardware_CPU":"Intel(R) Core(TM) i5-10400 CPU @ 2.90GHz","Hardware_CPU_Cores_Physical":6,"Hardware_CPU_Cores_Logical":12,"Hardware_RAM":17044029440,"Hardware_ComputerName":"K411","Config_IsEditor":true,"Config_IsUnattended":false,"Config_IsBuildMachine":false,"Config_IsRunningCommandlet":false,"Config_IsDebuggerPresent":false}
{"EventName":"Editor.AssetRegistry.Startup","TimestampUTC":1730546278.454000,"RecordId":1,"ProjectName":"Kukoverova_Veronika","ProjectID":"00000000000000000000000000000000","Session_ID":"{46A4D377-43C5-81E5-72CD-958C72118432}","Session_Label":"","Session_StartUTC":1730546273.763,"Build_Configuration":"Development","Build_IsInternalBuild":false,"Build_IsPerforceBuild":false,"Build_IsPromotedBuild":true,"Build_BranchName":"++ue5+release-5.4","Build_Changelist":35576357,"Hardware_Platform":"Windows","Hardware_GPU":"","Hardware_CPU":"Intel(R) Core(TM) i5-10400 CPU @ 2.90GHz","Hardware_CPU_Cores_Physical":6,"Hardware_CPU_Cores_Logical":12,"Hardware_RAM":17044029440,"Hardware_ComputerName":"K411","Config_IsEditor":true,"Config_IsUnattended":false,"Config_IsBuildMachine":false,"Config_IsRunningCommandlet":false,"Config_IsDebuggerPresent":false,"SchemaVersion":1,"Duration":0.002244,"StartedAsyncGather":true}
{"EventName":"Span","TimestampUTC":1730546283.766000,"RecordId":2,"ProjectName":"Kukoverova_Veronika","ProjectID":"00000000000000000000000000000000","Session_ID":"{46A4D377-43C5-81E5-72CD-958C72118432}","Session_Label":"","Session_StartUTC":1730546273.763,"Build_Configuration":"Development","Build_IsInternalBuild":false,"Build_IsPerforceBuild":false,"Build_IsPromotedBuild":true,"Build_BranchName":"++ue5+release-5.4","Build_Changelist":35576357,"Hardware_Platform":"Windows","Hardware_GPU":"","Hardware_CPU":"Intel(R) Core(TM) i5-10400 CPU @ 2.90GHz","Hardware_CPU_Cores_Physical":6,"Hardware_CPU_Cores_Logical":12,"Hardware_RAM":17044029440,"Hardware_ComputerName":"K411","Config_IsEditor":true,"Config_IsUnattended":false,"Config_IsBuildMachine":false,"Config_IsRunningCommandlet":false,"Config_IsDebuggerPresent":false,"MapName":"None","SchemaVersion":1,"Span_Name":"Editor.Boot","Span_GUID":"C9BCF339400FA88733CBAA977DC1291A","Span_ParentName":"Editor","Span_ThreadId":10688,"Span_Depth":2,"Span_StartUTC":1730546273.971,"Span_EndUTC":1730546283.766,"Span_TimeInSec":9.795}
{"EventName":"Core.Loading","TimestampUTC":1730546283.793000,"RecordId":3,"ProjectName":"Kukoverova_Veronika","ProjectID":"00000000000000000000000000000000","Session_ID":"{46A4D377-43C5-81E5-72CD-958C72118432}","Session_Label":"","Session_StartUTC":1730546273.763,"Build_Configuration":"Development","Build_IsInternalBuild":false,"Build_IsPerforceBuild":false,"Build_IsPromotedBuild":true,"Build_BranchName":"++ue5+release-5.4","Build_Changelist":35576357,"Hardware_Platform":"Windows","Hardware_GPU":"","Hardware_CPU":"Intel(R) Core(TM) i5-10400 CPU @ 2.90GHz","Hardware_CPU_Cores_Physical":6,"Hardware_CPU_Cores_Logical":12,"Hardware_RAM":17044029440,"Hardware_ComputerName":"K411","Config_IsEditor":true,"Config_IsUnattended":false,"Config_IsBuildMachine":false,"Config_IsRunningCommandlet":false,"Config_IsDebuggerPresent":false,"MapName":"None","SchemaVersion":3,"LoadingName":"BootEditor","LoadingSeconds":9.795,"DDC_Summary_BackEnd":"InstalledDerivedDataBackendGraph","DDC_Summary_HasLocalCache":"true","DDC_Summary_HasSharedCache":"false","DDC_Summary_HasCloudCache":"false","DDC_Summary_HasZenCache":"true","DDC_Summary_TotalGetHits":993.0,"DDC_Summary_TotalGetMisses":51.0,"DDC_Summary_TotalGets":1044.0,"DDC_Summary_TotalGetHitPct":0.951149,"DDC_Summary_GetMissPct":0.048851,"DDC_Summary_TotalPutHits":45.0,"DDC_Summary_TotalPutMisses":0.0,"DDC_Summary_TotalPuts":45.0,"DDC_Summary_TotalPutHitPct":1.0,"DDC_Summary_PutMissPct":0.0,"DDC_Summary_LocalGetHits":0.0,"DDC_Summary_LocalGetTotal":0.0,"DDC_Summary_LocalGetHitPct":0.0,"DDC_Summary_SharedGetHits":0.0,"DDC_Summary_SharedGetTotal":0.0,"DDC_Summary_SharedGetHitPct":0.0,"DDC_Summary_ZenLocalGetHits":305.0,"DDC_Summary_ZenLocalGetTotal":356.0,"DDC_Summary_ZenLocalGetHitPct":0.856742,"DDC_Summary_ZenRemoteGetHits":0.0,"DDC_Summary_ZenRemoteGetTotal":0.0,"DDC_Summary_ZenRemoteGetHitPct":0.0,"DDC_Summary_CloudGetHits":0.0,"DDC_Summary_CloudGetTotal":0.0,"DDC_Summary_CloudGetHitPct":0.0,"DDC_Summary_LocalLatency":0.0,"DDC_Summary_LocalReadSpeed":0.0,"DDC_Summary_LocalWriteSpeed":0.0,"DDC_Summary_SharedLatency":0.0,"DDC_Summary_SharedReadSpeed":0.0,"DDC_Summary_SharedWriteSpeed":0.0,"DDC_Summary_CloudLatency":0.0,"DDC_Summary_CloudReadSpeed":0.0,"DDC_Summary_CloudWriteSpeed":0.0}
{"EventName":"Core.DDC.Resource","TimestampUTC":1730546283.809000,"RecordId":4,"ProjectName":"Kukoverova_Veronika","ProjectID":"00000000000000000000000000000000","Session_ID":"{46A4D377-43C5-81E5-72CD-958C72118432}","Session_Label":"","Session_StartUTC":1730546273.763,"Build_Configuration":"Development","Build_IsInternalBuild":false,"Build_IsPerforceBuild":false,"Build_IsPromotedBuild":true,"Build_BranchName":"++ue5+release-5.4","Build_Changelist":35576357,"Hardware_Platform":"Windows","Hardware_GPU":"","Hardware_CPU":"Intel(R) Core(TM) i5-10400 CPU @ 2.90GHz","Hardware_CPU_Cores_Physical":6,"Hardware_CPU_Cores_Logical":12,"Hardware_RAM":17044029440,"Hardware_ComputerName":"K411","Config_IsEditor":true,"Config_IsUnattended":false,"Config_IsBuildMachine":false,"Config_IsRunningCommandlet":false,"Config_IsDebuggerPresent":false,"MapName":"None","SchemaVersion":3,"LoadingName":"BootEditor","AssetType":"Texture (Inline)","Load_Count":112,"Load_TimeSec":0.022298,"Load_SizeMB":52.478061,"Build_Count":0,"Build_TimeSec":0.0,"Build_SizeMB":0.0,"Total_Count":112,"Total_TimeSec":0.022298,"Total_SizeMB":52,"Efficiency":1.0,"Thread_TimeSec":0.022298}
{"EventName":"Core.DDC.Resource","TimestampUTC":1730546283.837000,"RecordId":5,"ProjectName":"Kukoverova_Veronika","ProjectID":"00000000000000000000000000000000","Session_ID":"{46A4D377-43C5-81E5-72CD-958C72118432}","Session_Label":"","Session_StartUTC":1730546273.763,"Build_Configuration":"Development","Build_IsInternalBuild":false,"Build_IsPerforceBuild":false,"Build_IsPromotedBuild":true,"Build_BranchName":"++ue5+release-5.4","Build_Changelist":35576357,"Hardware_Platform":"Windows","Hardware_GPU":"","Hardware_CPU":"Intel(R) Core(TM) i5-10400 CPU @ 2.90GHz","Hardware_CPU_Cores_Physical":6,"Hardware_CPU_Cores_Logical":12,"Hardware_RAM":17044029440,"Hardware_ComputerName":"K411","Config_IsEditor":true,"Config_IsUnattended":false,"Config_IsBuildMachine":false,"Config_IsRunningCommandlet":false,"Config_IsDebuggerPresent":false,"MapName":"None","SchemaVersion":3,"LoadingName":"BootEditor","AssetType":"Texture (Streaming)","Load_Count":30,"Load_TimeSec":0.006572,"Load_SizeMB":8.521484,"Build_Count":0,"Build_TimeSec":0.0,"Build_SizeMB":0.0,"Total_Count":30,"Total_TimeSec":0.006572,"Total_SizeMB":8,"Efficiency":1.0,"Thread_TimeSec":0.006572}
{"EventName":"Core.DDC.Resource","TimestampUTC":1730546283.853000,"RecordId":6,"ProjectName":"Kukoverova_Veronika","ProjectID":"00000000000000000000000000000000","Session_ID":"{46A4D377-43C5-81E5-72CD-958C72118432}","Session_Label":"","Session_StartUTC":1730546273.763,"Build_Configuration":"Development","Build_IsInternalBuild":false,"Build_IsPerforceBuild":false,"Build_IsPromotedBuild":true,"Build_BranchName":"++ue5+release-5.4","Build_Changelist":35576357,"Hardware_Platform":"Windows","Hardware_GPU":"","Hardware_CPU":"Intel(R) Core(TM) i5-10400 CPU @ 2.90GHz","Hardware_CPU_Cores_Physical":6,"Hardware_CPU_Cores_Logical":12,"Hardware_RAM":17044029440,"Hardware_ComputerName":"K411","Config_IsEditor":true,"Config_IsUnattended":false,"Config_IsBuildMachine":false,"Config_IsRunningCommandlet":false,"Config_IsDebuggerPresent":false,"MapName":"None","SchemaVersion":3,"LoadingName":"BootEditor","AssetType":"StaticMesh","Load_Count":47,"Load_TimeSec":0.030512,"Load_SizeMB":10.282331,"Build_Count":0,"Build_TimeSec":0.0,"Build_SizeMB":0.0,"Total_Count":47,"Total_TimeSec":0.030512,"Total_SizeMB":10,"Efficiency":1.0,"Thread_TimeSec":0.012337}
{"EventName":"Core.DDC.Resource","TimestampUTC":1730546283.915000,"RecordId":7,"ProjectName":"Kukoverova_Veronika","ProjectID":"00000000000000000000000000000000","Session_ID":"{46A4D377-43C5-81E5-72CD-958C72118432}","Session_Label":"","Session_StartUTC":1730546273.763,"Build_Configuration":"Development","Build_IsInternalBuild":false,"Build_IsPerforceBuild":false,"Build_IsPromotedBuild":true,"Build_BranchName":"++ue5+release-5.4","Build_Changelist":35576357,"Hardware_Platform":"Windows","Hardware_GPU":"","Hardware_CPU":"Intel(R) Core(TM) i5-10400 CPU @ 2.90GHz","Hardware_CPU_Cores_Physical":6,"Hardware_CPU_Cores_Logical":12,"Hardware_RAM":17044029440,"Hardware_ComputerName":"K411","Config_IsEditor":true,"Config_IsUnattended":false,"Config_IsBuildMachine":false,"Config_IsRunningCommandlet":false,"Config_IsDebuggerPresent":false,"MapName":"None","SchemaVersion":3,"LoadingName":"BootEditor","AssetType":"GlobalShader","Load_Count":304,"Load_TimeSec":0.083614,"Load_SizeMB":79.224675,"Build_Count":0,"Build_TimeSec":0.0,"Build_SizeMB":0.0,"Total_Count":304,"Total_TimeSec":0.083614,"Total_SizeMB":79,"Efficiency":1.0,"Thread_TimeSec":0.083614}
{"EventName":"Core.DDC.Resource","TimestampUTC":1730546283.947000,"RecordId":8,"ProjectName":"Kukoverova_Veronika","ProjectID":"00000000000000000000000000000000","Session_ID":"{46A4D377-43C5-81E5-72CD-958C72118432}","Session_Label":"","Session_StartUTC":1730546273.763,"Build_Configuration":"Development","Build_IsInternalBuild":false,"Build_IsPerforceBuild":false,"Build_IsPromotedBuild":true,"Build_BranchName":"++ue5+release-5.4","Build_Changelist":35576357,"Hardware_Platform":"Windows","Hardware_GPU":"","Hardware_CPU":"Intel(R) Core(TM) i5-10400 CPU @ 2.90GHz","Hardware_CPU_Cores_Physical":6,"Hardware_CPU_Cores_Logical":12,"Hardware_RAM":17044029440,"Hardware_ComputerName":"K411","Config_IsEditor":true,"Config_IsUnattended":false,"Config_IsBuildMachine":false,"Config_IsRunningCommandlet":false,"Config_IsDebuggerPresent":false,"MapName":"None","SchemaVersion":3,"LoadingName":"BootEditor","AssetType":"BodySetup","Load_Count":10,"Load_TimeSec":0.012818,"Load_SizeMB":5.461349,"Build_Count":0,"Build_TimeSec":0.0,"Build_SizeMB":0.0,"Total_Count":10,"Total_TimeSec":0.012818,"Total_SizeMB":5,"Efficiency":1.0,"Thread_TimeSec":0.002488}
{"EventName":"Core.DDC.Resource","TimestampUTC":1730546283.981000,"RecordId":9,"ProjectName":"Kukoverova_Veronika","ProjectID":"00000000000000000000000000000000","Session_ID":"{46A4D377-43C5-81E5-72CD-958C72118432}","Session_Label":"","Session_StartUTC":1730546273.763,"Build_Configuration":"Development","Build_IsInternalBuild":false,"Build_IsPerforceBuild":false,"Build_IsPromotedBuild":true,"Build_BranchName":"++ue5+release-5.4","Build_Changelist":35576357,"Hardware_Platform":"Windows","Hardware_GPU":"","Hardware_CPU":"Intel(R) Core(TM) i5-10400 CPU @ 2.90GHz","Hardware_CPU_Cores_Physical":6,"Hardware_CPU_Cores_Logical":12,"Hardware_RAM":17044029440,"Hardware_ComputerName":"K411","Config_IsEditor":true,"Config_IsUnattended":false,"Config_IsBuildMachine":false,"Config_IsRunningCommandlet":false,"Config_IsDebuggerPresent":false,"MapName":"None","SchemaVersion":3,"LoadingName":"BootEditor","AssetType":"CardRepresentation","Load_Count":47,"Load_TimeSec":0.003054,"Load_SizeMB":0.014364,"Build_Count":0,"Build_TimeSec":0.0,"Build_SizeMB":0.0,"Total_Count":47,"Total_TimeSec":0.003054,"Total_SizeMB":0,"Efficiency":1.0,"Thread_TimeSec":0.002317}
{"EventName":"Core.DDC.Resource","TimestampUTC":1730546284.014000,"RecordId":10,"ProjectName":"Kukoverova_Veronika","ProjectID":"00000000000000000000000000000000","Session_ID":"{46A4D377-43C5-81E5-72CD-958C72118432}","Session_Label":"","Session_StartUTC":1730546273.763,"Build_Configuration":"Development","Build_IsInternalBuild":false,"Build_IsPerforceBuild":false,"Build_IsPromotedBuild":true,"Build_BranchName":"++ue5+release-5.4","Build_Changelist":35576357,"Hardware_Platform":"Windows","Hardware_GPU":"","Hardware_CPU":"Intel(R) Core(TM) i5-10400 CPU @ 2.90GHz","Hardware_CPU_Cores_Physical":6,"Hardware_CPU_Cores_Logical":12,"Hardware_RAM":17044029440,"Hardware_ComputerName":"K411","Config_IsEditor":true,"Config_IsUnattended":false,"Config_IsBuildMachine":false,"Config_IsRunningCommandlet":false,"Config_IsDebuggerPresent":false,"MapName":"None","SchemaVersion":3,"LoadingName":"BootEditor","AssetType":"MaterialShader","Load_Count":4,"Load_TimeSec":0.014892,"Load_SizeMB":19.752317,"Build_Count":0,"Build_TimeSec":0.0,"Build_SizeMB":0.0,"Total_Count":4,"Total_TimeSec":0.014892,"Total_SizeMB":19,"Efficiency":1.0,"Thread_TimeSec":0.014892}
{"EventName":"Core.DDC.Resource","TimestampUTC":1730546284.048000,"RecordId":11,"ProjectName":"Kukoverova_Veronika","ProjectID":"00000000000000000000000000000000","Session_ID":"{46A4D377-43C5-81E5-72CD-958C72118432}","Session_Label":"","Session_StartUTC":1730546273.763,"Build_Configuration":"Development","Build_IsInternalBuild":false,"Build_IsPerforceBuild":false,"Build_IsPromotedBuild":true,"Build_BranchName":"++ue5+release-5.4","Build_Changelist":35576357,"Hardware_Platform":"Windows","Hardware_GPU":"","Hardware_CPU":"Intel(R) Core(TM) i5-10400 CPU @ 2.90GHz","Hardware_CPU_Cores_Physical":6,"Hardware_CPU_Cores_Logical":12,"Hardware_RAM":17044029440,"Hardware_ComputerName":"K411","Config_IsEditor":true,"Config_IsUnattended":false,"Config_IsBuildMachine":false,"Config_IsRunningCommandlet":false,"Config_IsDebuggerPresent":false,"MapName":"None","SchemaVersion":3,"LoadingName":"BootEditor","AssetType":"DistanceField","Load_Count":47,"Load_TimeSec":0.014094,"Load_SizeMB":3.886359,"Build_Count":0,"Build_TimeSec":0.0,"Build_SizeMB":0.0,"Total_Count":47,"Total_TimeSec":0.014094,"Total_SizeMB":3,"Efficiency":1.0,"Thread_TimeSec":0.011532}
{"EventName":"Core.DDC.Resource","TimestampUTC":1730546284.081000,"RecordId":12,"ProjectName":"Kukoverova_Veronika","ProjectID":"00000000000000000000000000000000","Session_ID":"{46A4D377-43C5-81E5-72CD-958C72118432}","Session_Label":"","Session_StartUTC":1730546273.763,"Build_Configuration":"Development","Build_IsInternalBuild":false,"Build_IsPerforceBuild":false,"Build_IsPromotedBuild":true,"Build_BranchName":"++ue5+release-5.4","Build_Changelist":35576357,"Hardware_Platform":"Windows","Hardware_GPU":"","Hardware_CPU":"Intel(R) Core(TM) i5-10400 CPU @ 2.90GHz","Hardware_CPU_Cores_Physical":6,"Hardware_CPU_Cores_Logical":12,"Hardware_RAM":17044029440,"Hardware_ComputerName":"K411","Config_IsEditor":true,"Config_IsUnattended":false,"Config_IsBuildMachine":false,"Config_IsRunningCommandlet":false,"Config_IsDebuggerPresent":false,"MapName":"None","SchemaVersion":3,"LoadingName":"BootEditor","AssetType":"Audio (Inline)","Load_Count":8,"Load_TimeSec":0.003188,"Load_SizeMB":0.006736,"Build_Count":0,"Build_TimeSec":0.0,"Build_SizeMB":0.0,"Total_Count":8,"Total_TimeSec":0.003188,"Total_SizeMB":0,"Efficiency":1.0,"Thread_TimeSec":0.003188}
{"EventName":"Core.DDC.Resource","TimestampUTC":1730546284.115000,"RecordId":13,"ProjectName":"Kukoverova_Veronika","ProjectID":"00000000000000000000000000000000","Session_ID":"{46A4D377-43C5-81E5-72CD-958C72118432}","Session_Label":"","Session_StartUTC":1730546273.763,"Build_Configuration":"Development","Build_IsInternalBuild":false,"Build_IsPerforceBuild":false,"Build_IsPromotedBuild":true,"Build_BranchName":"++ue5+release-5.4","Build_Changelist":35576357,"Hardware_Platform":"Windows","Hardware_GPU":"","Hardware_CPU":"Intel(R) Core(TM) i5-10400 CPU @ 2.90GHz","Hardware_CPU_Cores_Physical":6,"Hardware_CPU_Cores_Logical":12,"Hardware_RAM":17044029440,"Hardware_ComputerName":"K411","Config_IsEditor":true,"Config_IsUnattended":false,"Config_IsBuildMachine":false,"Config_IsRunningCommandlet":false,"Config_IsDebuggerPresent":false,"MapName":"None","SchemaVersion":3,"LoadingName":"BootEditor","AssetType":"NavCollision","Load_Count":47,"Load_TimeSec":0.003056,"Load_SizeMB":0.062785,"Build_Count":0,"Build_TimeSec":0.0,"Build_SizeMB":0.0,"Total_Count":47,"Total_TimeSec":0.003056,"Total_SizeMB":0,"Efficiency":1.0,"Thread_TimeSec":0.00191}
{"EventName":"Core.DDC.Resource","TimestampUTC":1730546284.148000,"RecordId":14,"ProjectName":"Kukoverova_Veronika","ProjectID":"00000000000000000000000000000000","Session_ID":"{46A4D377-43C5-81E5-72CD-958C72118432}","Session_Label":"","Session_StartUTC":1730546273.763,"Build_Configuration":"Development","Build_IsInternalBuild":false,"Build_IsPerforceBuild":false,"Build_IsPromotedBuild":true,"Build_BranchName":"++ue5+release-5.4","Build_Changelist":35576357,"Hardware_Platform":"Windows","Hardware_GPU":"","Hardware_CPU":"Intel(R) Core(TM) i5-10400 CPU @ 2.90GHz","Hardware_CPU_Cores_Physical":6,"Hardware_CPU_Cores_Logical":12,"Hardware_RAM":17044029440,"Hardware_ComputerName":"K411","Config_IsEditor":true,"Config_IsUnattended":false,"Config_IsBuildMachine":false,"Config_IsRunningCommandlet":false,"Config_IsDebuggerPresent":false,"MapName":"None","SchemaVersion":3,"LoadingName":"BootEditor","AssetType":"Total","Load_Count":656,"Load_TimeSec":0.194098,"Load_SizeMB":179.690461,"Build_Count":0,"Build_TimeSec":0.0,"Build_SizeMB":0.0,"Total_Count":656,"Total_TimeSec":0.194098,"Total_SizeMB":179,"Efficiency":1.0,"Thread_TimeSec":0.161148}
{"EventName":"Core.DDC.Summary","TimestampUTC":1730546284.183000,"RecordId":15,"ProjectName":"Kukoverova_Veronika","ProjectID":"00000000000000000000000000000000","Session_ID":"{46A4D377-43C5-81E5-72CD-958C72118432}","Session_Label":"","Session_StartUTC":1730546273.763,"Build_Configuration":"Development","Build_IsInternalBuild":false,"Build_IsPerforceBuild":false,"Build_IsPromotedBuild":true,"Build_BranchName":"++ue5+release-5.4","Build_Changelist":35576357,"Hardware_Platform":"Windows","Hardware_GPU":"","Hardware_CPU":"Intel(R) Core(TM) i5-10400 CPU @ 2.90GHz","Hardware_CPU_Cores_Physical":6,"Hardware_CPU_Cores_Logical":12,"Hardware_RAM":17044029440,"Hardware_ComputerName":"K411","Config_IsEditor":true,"Config_IsUnattended":false,"Config_IsBuildMachine":false,"Config_IsRunningCommandlet":false,"Config_IsDebuggerPresent":false,"MapName":"None","SchemaVersion":3,"LoadingName":"BootEditor","BackEnd":"InstalledDerivedDataBackendGraph","HasLocalCache":"true","HasSharedCache":"false","HasCloudCache":"false","HasZenCache":"true","TotalGetHits":993.0,"TotalGetMisses":51.0,"TotalGets":1044.0,"TotalGetHitPct":0.951149,"GetMissPct":0.048851,"TotalPutHits":45.0,"TotalPutMisses":0.0,"TotalPuts":45.0,"TotalPutHitPct":1.0,"PutMissPct":0.0,"LocalGetHits":0.0,"LocalGetTotal":0.0,"LocalGetHitPct":0.0,"SharedGetHits":0.0,"SharedGetTotal":0.0,"SharedGetHitPct":0.0,"ZenLocalGetHits":305.0,"ZenLocalGetTotal":356.0,"ZenLocalGetHitPct":0.856742,"ZenRemoteGetHits":0.0,"ZenRemoteGetTotal":0.0,"ZenRemoteGetHitPct":0.0,"CloudGetHits":0.0,"CloudGetTotal":0.0,"CloudGetHitPct":0.0,"LocalLatency":0.0,"LocalReadSpeed":0.0,"LocalWriteSpeed":0.0,"SharedLatency":0.0,"SharedReadSpeed":0.0,"SharedWriteSpeed":0.0,"CloudLatency":0.0,"CloudReadSpeed":0.0,"CloudWriteSpeed":0.0}
{"EventName":"Core.Zen","TimestampUTC":1730546284.214000,"RecordId":16,"ProjectName":"Kukoverova_Veronika","ProjectID":"00000000000000000000000000000000","Session_ID":"{46A4D377-43C5-81E5-72CD-958C72118432}","Session_Label":"","Session_StartUTC":1730546273.763,"Build_Configuration":"Development","Build_IsInternalBuild":false,"Build_IsPerforceBuild":false,"Build_IsPromotedBuild":true,"Build_BranchName":"++ue5+release-5.4","Build_Changelist":35576357,"Hardware_Platform":"Windows","Hardware_GPU":"","Hardware_CPU":"Intel(R) Core(TM) i5-10400 CPU @ 2.90GHz","Hardware_CPU_Cores_Physical":6,"Hardware_CPU_Cores_Logical":12,"Hardware_RAM":17044029440,"Hardware_ComputerName":"K411","Config_IsEditor":true,"Config_IsUnattended":false,"Config_IsBuildMachine":false,"Config_IsRunningCommandlet":false,"Config_IsDebuggerPresent":false,"MapName":"None","SchemaVersion":1,"LoadingName":"BootEditor","Zen_Enabled":true,"Zen_Cache_Size_Disk":168316183.0,"Zen_Cache_Size_Memory":0.0,"Zen_Cache_Hits":0,"Zen_Cache_Misses":0,"Zen_Cache_Writes":0,"Zen_Cache_HitRatio":0.0,"Zen_Cache_Cas_Hits":0,"Zen_Cache_Cas_Misses":0,"Zen_Cache_Cas_Writes":0,"Zen_Cache_Requests":0,"Zen_Cache_BadRequests":0,"Zen_Cache_Requests_Count":0,"Zen_Cache_Requests_RateMean":0.0,"Zen_Cache_Requests_TAverage":0.0,"Zen_Cache_Requests_TMin":0.0,"Zen_Cache_Requests_TMax":0.0,"Zen_Cache_TotalUploadedMB":0.0,"Zen_Upstream_TotalDownloadedMB":0.0,"Zen_Upstream_TotalUploadedMB":0.0,"Zen_Upstream_Requests_Count":0,"Zen_Upstream_Requests_RateMean":0.0,"Zen_Upstream_Requests_TAverage":0.0,"Zen_Upstream_Requests_TMin":0.0,"Zen_Upstream_Requests_TMax":0.0,"Zen_Cas_Size_Large":0,"Zen_Cas_Size_Small":182141384,"Zen_Cas_Size_Tiny":132153,"Zen_Cas_Size_Total":182273537,"Zen_Project_Size_Disk":0.0,"Zen_Project_Size_Memory":0.0,"Zen_Project_WriteCount":0,"Zen_Project_ReadCount":0,"Zen_Project_DeleteCount":0,"Zen_Project_Oplog_WriteCount":0,"Zen_Project_Oplog_ReadCount":0,"Zen_Project_Oplog_DeleteCount":0,"Zen_Project_Op_Hits":0,"Zen_Project_Op_Misses":0,"Zen_Project_Op_Writes":0,"Zen_Project_Chunk_Hits":0,"Zen_Project_Chunk_Misses":0,"Zen_Project_Chunk_Writes":0,"Zen_Project_Requests":0,"Zen_Project_BadRequests":0,"Zen_Project_Op_HitRatio":0.0,"Zen_Project_Chunk_HitRatio":0.0}
{"EventName":"Span","TimestampUTC":1730546285.349000,"RecordId":17,"ProjectName":"Kukoverova_Veronika","ProjectID":"00000000000000000000000000000000","Session_ID":"{46A4D377-43C5-81E5-72CD-958C72118432}","Session_Label":"","Session_StartUTC":1730546273.763,"Build_Configuration":"Development","Build_IsInternalBuild":false,"Build_IsPerforceBuild":false,"Build_IsPromotedBuild":true,"Build_BranchName":"++ue5+release-5.4","Build_Changelist":35576357,"Hardware_Platform":"Windows","Hardware_GPU":"","Hardware_CPU":"Intel(R) Core(TM) i5-10400 CPU @ 2.90GHz","Hardware_CPU_Cores_Physical":6,"Hardware_CPU_Cores_Logical":12,"Hardware_RAM":17044029440,"Hardware_ComputerName":"K411","Config_IsEditor":true,"Config_IsUnattended":false,"Config_IsBuildMachine":false,"Config_IsRunningCommandlet":false,"Config_IsDebuggerPresent":false,"MapName":"VRTemplateMap","SchemaVersion":1,"Span_Name":"Editor.LoadMap","Span_GUID":"C504DEF946C11759FE84368B53F37803","Span_ParentName":"Editor","Span_ThreadId":10688,"Span_Depth":3,"Span_StartUTC":1730546284.248,"Span_EndUTC":1730546285.349,"Span_TimeInSec":1.101}
{"EventName":"Core.Loading","TimestampUTC":1730546285.393000,"RecordId":18,"ProjectName":"Kukoverova_Veronika","ProjectID":"00000000000000000000000000000000","Session_ID":"{46A4D377-43C5-81E5-72CD-958C72118432}","Session_Label":"","Session_StartUTC":1730546273.763,"Build_Configuration":"Development","Build_IsInternalBuild":false,"Build_IsPerforceBuild":false,"Build_IsPromotedBuild":true,"Build_BranchName":"++ue5+release-5.4","Build_Changelist":35576357,"Hardware_Platform":"Windows","Hardware_GPU":"","Hardware_CPU":"Intel(R) Core(TM) i5-10400 CPU @ 2.90GHz","Hardware_CPU_Cores_Physical":6,"Hardware_CPU_Cores_Logical":12,"Hardware_RAM":17044029440,"Hardware_ComputerName":"K411","Config_IsEditor":true,"Config_IsUnattended":false,"Config_IsBuildMachine":false,"Config_IsRunningCommandlet":false,"Config_IsDebuggerPresent":false,"MapName":"VRTemplateMap","SchemaVersion":3,"LoadingName":"LoadMap","LoadingSeconds":1.101,"Zen_Enabled":true,"Zen_Cache_Size_Disk":168316183.0,"Zen_Cache_Size_Memory":0.0,"Zen_Cache_Hits":0,"Zen_Cache_Misses":0,"Zen_Cache_Writes":0,"Zen_Cache_HitRatio":0.0,"Zen_Cache_Cas_Hits":0,"Zen_Cache_Cas_Misses":0,"Zen_Cache_Cas_Writes":0,"Zen_Cache_Requests":0,"Zen_Cache_BadRequests":0,"Zen_Cache_Requests_Count":0,"Zen_Cache_Requests_RateMean":0.0,"Zen_Cache_Requests_TAverage":0.0,"Zen_Cache_Requests_TMin":0.0,"Zen_Cache_Requests_TMax":0.0,"Zen_Cache_TotalUploadedMB":0.0,"Zen_Upstream_TotalDownloadedMB":0.0,"Zen_Upstream_TotalUploadedMB":0.0,"Zen_Upstream_Requests_Count":0,"Zen_Upstream_Requests_RateMean":0.0,"Zen_Upstream_Requests_TAverage":0.0,"Zen_Upstream_Requests_TMin":0.0,"Zen_Upstream_Requests_TMax":0.0,"Zen_Cas_Size_Large":0,"Zen_Cas_Size_Small":182141384,"Zen_Cas_Size_Tiny":132153,"Zen_Cas_Size_Total":182273537,"Zen_Project_Size_Disk":0.0,"Zen_Project_Size_Memory":0.0,"Zen_Project_WriteCount":0,"Zen_Project_ReadCount":0,"Zen_Project_DeleteCount":0,"Zen_Project_Oplog_WriteCount":0,"Zen_Project_Oplog_ReadCount":0,"Zen_Project_Oplog_DeleteCount":0,"Zen_Project_Op_Hits":0,"Zen_Project_Op_Misses":0,"Zen_Project_Op_Writes":0,"Zen_Project_Chunk_Hits":0,"Zen_Project_Chunk_Misses":0,"Zen_Project_Chunk_Writes":0,"Zen_Project_Requests":0,"Zen_Project_BadRequests":0,"Zen_Project_Op_HitRatio":0.0,"Zen_Project_Chunk_HitRatio":0.0,"DDC_Summary_BackEnd":"InstalledDerivedDataBackendGraph","DDC_Summary_HasLocalCache":"true","DDC_Summary_HasSharedCache":"false","DDC_Summary_HasCloudCache":"false","DDC_Summary_HasZenCache":"true","DDC_Summary_TotalGetHits":1171.0,"DDC_Summary_TotalGetMisses":57.0,"DDC_Summary_TotalGets":1228.0,"DDC_Summary_TotalGetHitPct":0.953583,"DDC_Summary_GetMissPct":0.046417,"DDC_Summary_TotalPutHits":51.0,"DDC_Summary_TotalPutMisses":0.0,"DDC_Summary_TotalPuts":51.0,"DDC_Summary_TotalPutHitPct":1.0,"DDC_Summary_PutMissPct":0.0,"DDC_Summary_LocalGetHits":0.0,"DDC_Summary_LocalGetTotal":0.0,"DDC_Summary_LocalGetHitPct":0.0,"DDC_Summary_SharedGetHits":0.0,"DDC_Summary_SharedGetTotal":0.0,"DDC_Summary_SharedGetHitPct":0.0,"DDC_Summary_ZenLocalGetHits":410.0,"DDC_Summary_ZenLocalGetTotal":467.0,"DDC_Summary_ZenLocalGetHitPct":0.877944,"DDC_Summary_ZenRemoteGetHits":0.0,"DDC_Summary_ZenRemoteGetTotal":0.0,"DDC_Summary_ZenRemoteGetHitPct":0.0,"DDC_Summary_CloudGetHits":0.0,"DDC_Summary_CloudGetTotal":0.0,"DDC_Summary_CloudGetHitPct":0.0,"DDC_Summary_LocalLatency":0.0,"DDC_Summary_LocalReadSpeed":0.0,"DDC_Summary_LocalWriteSpeed":0.0,"DDC_Summary_SharedLatency":0.0,"DDC_Summary_SharedReadSpeed":0.0,"DDC_Summary_SharedWriteSpeed":0.0,"DDC_Summary_CloudLatency":0.0,"DDC_Summary_CloudReadSpeed":0.0,"DDC_Summary_CloudWriteSpeed":0.0}
{"EventName":"Core.DDC.Resource","TimestampUTC":1730546285.407000,"RecordId":19,"ProjectName":"Kukoverova_Veronika","ProjectID":"00000000000000000000000000000000","Session_ID":"{46A4D377-43C5-81E5-72CD-958C72118432}","Session_Label":"","Session_StartUTC":1730546273.763,"Build_Configuration":"Development","Build_IsInternalBuild":false,"Build_IsPerforceBuild":false,"Build_IsPromotedBuild":true,"Build_BranchName":"++ue5+release-5.4","Build_Changelist":35576357,"Hardware_Platform":"Windows","Hardware_GPU":"","Hardware_CPU":"Intel(R) Core(TM) i5-10400 CPU @ 2.90GHz","Hardware_CPU_Cores_Physical":6,"Hardware_CPU_Cores_Logical":12,"Hardware_RAM":17044029440,"Hardware_ComputerName":"K411","Config_IsEditor":true,"Config_IsUnattended":false,"Config_IsBuildMachine":false,"Config_IsRunningCommandlet":false,"Config_IsDebuggerPresent":false,"MapName":"VRTemplateMap","SchemaVersion":3,"LoadingName":"LoadMap","AssetType":"Texture (Inline)","Load_Count":113,"Load_TimeSec":0.022697,"Load_SizeMB":52.509381,"Build_Count":0,"Build_TimeSec":0.0,"Build_SizeMB":0.0,"Total_Count":113,"Total_TimeSec":0.022697,"Total_SizeMB":52,"Efficiency":1.0,"Thread_TimeSec":0.022697}
{"EventName":"Core.DDC.Resource","TimestampUTC":1730546285.426000,"RecordId":20,"ProjectName":"Kukoverova_Veronika","ProjectID":"00000000000000000000000000000000","Session_ID":"{46A4D377-43C5-81E5-72CD-958C72118432}","Session_Label":"","Session_StartUTC":1730546273.763,"Build_Configuration":"Development","Build_IsInternalBuild":false,"Build_IsPerforceBuild":false,"Build_IsPromotedBuild":true,"Build_BranchName":"++ue5+release-5.4","Build_Changelist":35576357,"Hardware_Platform":"Windows","Hardware_GPU":"","Hardware_CPU":"Intel(R) Core(TM) i5-10400 CPU @ 2.90GHz","Hardware_CPU_Cores_Physical":6,"Hardware_CPU_Cores_Logical":12,"Hardware_RAM":17044029440,"Hardware_ComputerName":"K411","Config_IsEditor":true,"Config_IsUnattended":false,"Config_IsBuildMachine":false,"Config_IsRunningCommandlet":false,"Config_IsDebuggerPresent":false,"MapName":"VRTemplateMap","SchemaVersion":3,"LoadingName":"LoadMap","AssetType":"Texture (Streaming)","Load_Count":30,"Load_TimeSec":0.006572,"Load_SizeMB":8.521484,"Build_Count":0,"Build_TimeSec":0.0,"Build_SizeMB":0.0,"Total_Count":30,"Total_TimeSec":0.006572,"Total_SizeMB":8,"Efficiency":1.0,"Thread_TimeSec":0.006572}
{"EventName":"Core.DDC.Resource","TimestampUTC":1730546285.448000,"RecordId":21,"ProjectName":"Kukoverova_Veronika","ProjectID":"00000000000000000000000000000000","Session_ID":"{46A4D377-43C5-81E5-72CD-958C72118432}","Session_Label":"","Session_StartUTC":1730546273.763,"Build_Configuration":"Development","Build_IsInternalBuild":false,"Build_IsPerforceBuild":false,"Build_IsPromotedBuild":true,"Build_BranchName":"++ue5+release-5.4","Build_Changelist":35576357,"Hardware_Platform":"Windows","Hardware_GPU":"","Hardware_CPU":"Intel(R) Core(TM) i5-10400 CPU @ 2.90GHz","Hardware_CPU_Cores_Physical":6,"Hardware_CPU_Cores_Logical":12,"Hardware_RAM":17044029440,"Hardware_ComputerName":"K411","Config_IsEditor":true,"Config_IsUnattended":false,"Config_IsBuildMachine":false,"Config_IsRunningCommandlet":false,"Config_IsDebuggerPresent":false,"MapName":"VRTemplateMap","SchemaVersion":3,"LoadingName":"LoadMap","AssetType":"StaticMesh","Load_Count":53,"Load_TimeSec":0.034145,"Load_SizeMB":11.455413,"Build_Count":0,"Build_TimeSec":0.0,"Build_SizeMB":0.0,"Total_Count":53,"Total_TimeSec":0.034145,"Total_SizeMB":11,"Efficiency":1.0,"Thread_TimeSec":0.012337}
{"EventName":"Core.DDC.Resource","TimestampUTC":1730546285.463000,"RecordId":22,"ProjectName":"Kukoverova_Veronika","ProjectID":"00000000000000000000000000000000","Session_ID":"{46A4D377-43C5-81E5-72CD-958C72118432}","Session_Label":"","Session_StartUTC":1730546273.763,"Build_Configuration":"Development","Build_IsInternalBuild":false,"Build_IsPerforceBuild":false,"Build_IsPromotedBuild":true,"Build_BranchName":"++ue5+release-5.4","Build_Changelist":35576357,"Hardware_Platform":"Windows","Hardware_GPU":"","Hardware_CPU":"Intel(R) Core(TM) i5-10400 CPU @ 2.90GHz","Hardware_CPU_Cores_Physical":6,"Hardware_CPU_Cores_Logical":12,"Hardware_RAM":17044029440,"Hardware_ComputerName":"K411","Config_IsEditor":true,"Config_IsUnattended":false,"Config_IsBuildMachine":false,"Config_IsRunningCommandlet":false,"Config_IsDebuggerPresent":false,"MapName":"VRTemplateMap","SchemaVersion":3,"LoadingName":"LoadMap","AssetType":"SkeletalMesh","Load_Count":3,"Load_TimeSec":0.020559,"Load_SizeMB":4.835098,"Build_Count":0,"Build_TimeSec":0.0,"Build_SizeMB":0.0,"Total_Count":3,"Total_TimeSec":0.020559,"Total_SizeMB":4,"Efficiency":1.0,"Thread_TimeSec":0.0}
{"EventName":"Core.DDC.Resource","TimestampUTC":1730546285.492000,"RecordId":23,"ProjectName":"Kukoverova_Veronika","ProjectID":"00000000000000000000000000000000","Session_ID":"{46A4D377-43C5-81E5-72CD-958C72118432}","Session_Label":"","Session_StartUTC":1730546273.763,"Build_Configuration":"Development","Build_IsInternalBuild":false,"Build_IsPerforceBuild":false,"Build_IsPromotedBuild":true,"Build_BranchName":"++ue5+release-5.4","Build_Changelist":35576357,"Hardware_Platform":"Windows","Hardware_GPU":"","Hardware_CPU":"Intel(R) Core(TM) i5-10400 CPU @ 2.90GHz","Hardware_CPU_Cores_Physical":6,"Hardware_CPU_Cores_Logical":12,"Hardware_RAM":17044029440,"Hardware_ComputerName":"K411","Config_IsEditor":true,"Config_IsUnattended":false,"Config_IsBuildMachine":false,"Config_IsRunningCommandlet":false,"Config_IsDebuggerPresent":false,"MapName":"VRTemplateMap","SchemaVersion":3,"LoadingName":"LoadMap","AssetType":"GlobalShader","Load_Count":304,"Load_TimeSec":0.083614,"Load_SizeMB":79.224675,"Build_Count":0,"Build_TimeSec":0.0,"Build_SizeMB":0.0,"Total_Count":304,"Total_TimeSec":0.083614,"Total_SizeMB":79,"Efficiency":1.0,"Thread_TimeSec":0.083614}
{"EventName":"Core.DDC.Resource","TimestampUTC":1730546285.515000,"RecordId":24,"ProjectName":"Kukoverova_Veronika","ProjectID":"00000000000000000000000000000000","Session_ID":"{46A4D377-43C5-81E5-72CD-958C72118432}","Session_Label":"","Session_StartUTC":1730546273.763,"Build_Configuration":"Development","Build_IsInternalBuild":false,"Build_IsPerforceBuild":false,"Build_IsPromotedBuild":true,"Build_BranchName":"++ue5+release-5.4","Build_Changelist":35576357,"Hardware_Platform":"Windows","Hardware_GPU":"","Hardware_CPU":"Intel(R) Core(TM) i5-10400 CPU @ 2.90GHz","Hardware_CPU_Cores_Physical":6,"Hardware_CPU_Cores_Logical":12,"Hardware_RAM":17044029440,"Hardware_ComputerName":"K411","Config_IsEditor":true,"Config_IsUnattended":false,"Config_IsBuildMachine":false,"Config_IsRunningCommandlet":false,"Config_IsDebuggerPresent":false,"MapName":"VRTemplateMap","SchemaVersion":3,"LoadingName":"LoadMap","AssetType":"BodySetup","Load_Count":12,"Load_TimeSec":0.014659,"Load_SizeMB":6.161453,"Build_Count":0,"Build_TimeSec":0.0,"Build_SizeMB":0.0,"Total_Count":12,"Total_TimeSec":0.014659,"Total_SizeMB":6,"Efficiency":1.0,"Thread_TimeSec":0.002488}
{"EventName":"Core.DDC.Resource","TimestampUTC":1730546285.548000,"RecordId":25,"ProjectName":"Kukoverova_Veronika","ProjectID":"00000000000000000000000000000000","Session_ID":"{46A4D377-43C5-81E5-72CD-958C72118432}","Session_Label":"","Session_StartUTC":1730546273.763,"Build_Configuration":"Development","Build_IsInternalBuild":false,"Build_IsPerforceBuild":false,"Build_IsPromotedBuild":true,"Build_BranchName":"++ue5+release-5.4","Build_Changelist":35576357,"Hardware_Platform":"Windows","Hardware_GPU":"","Hardware_CPU":"Intel(R) Core(TM) i5-10400 CPU @ 2.90GHz","Hardware_CPU_Cores_Physical":6,"Hardware_CPU_Cores_Logical":12,"Hardware_RAM":17044029440,"Hardware_ComputerName":"K411","Config_IsEditor":true,"Config_IsUnattended":false,"Config_IsBuildMachine":false,"Config_IsRunningCommandlet":false,"Config_IsDebuggerPresent":false,"MapName":"VRTemplateMap","SchemaVersion":3,"LoadingName":"LoadMap","AssetType":"CardRepresentation","Load_Count":53,"Load_TimeSec":0.003299,"Load_SizeMB":0.016319,"Build_Count":0,"Build_TimeSec":0.0,"Build_SizeMB":0.0,"Total_Count":53,"Total_TimeSec":0.003299,"Total_SizeMB":0,"Efficiency":1.0,"Thread_TimeSec":0.002317}
{"EventName":"Core.DDC.Resource","TimestampUTC":1730546285.571000,"RecordId":26,"ProjectName":"Kukoverova_Veronika","ProjectID":"00000000000000000000000000000000","Session_ID":"{46A4D377-43C5-81E5-72CD-958C72118432}","Session_Label":"","Session_StartUTC":1730546273.763,"Build_Configuration":"Development","Build_IsInternalBuild":false,"Build_IsPerforceBuild":false,"Build_IsPromotedBuild":true,"Build_BranchName":"++ue5+release-5.4","Build_Changelist":35576357,"Hardware_Platform":"Windows","Hardware_GPU":"","Hardware_CPU":"Intel(R) Core(TM) i5-10400 CPU @ 2.90GHz","Hardware_CPU_Cores_Physical":6,"Hardware_CPU_Cores_Logical":12,"Hardware_RAM":17044029440,"Hardware_ComputerName":"K411","Config_IsEditor":true,"Config_IsUnattended":false,"Config_IsBuildMachine":false,"Config_IsRunningCommandlet":false,"Config_IsDebuggerPresent":false,"MapName":"VRTemplateMap","SchemaVersion":3,"LoadingName":"LoadMap","AssetType":"MaterialShader","Load_Count":4,"Load_TimeSec":0.014892,"Load_SizeMB":19.752317,"Build_Count":0,"Build_TimeSec":0.0,"Build_SizeMB":0.0,"Total_Count":4,"Total_TimeSec":0.014892,"Total_SizeMB":19,"Efficiency":1.0,"Thread_TimeSec":0.014892}
{"EventName":"Core.DDC.Resource","TimestampUTC":1730546285.603000,"RecordId":27,"ProjectName":"Kukoverova_Veronika","ProjectID":"00000000000000000000000000000000","Session_ID":"{46A4D377-43C5-81E5-72CD-958C72118432}","Session_Label":"","Session_StartUTC":1730546273.763,"Build_Configuration":"Development","Build_IsInternalBuild":false,"Build_IsPerforceBuild":false,"Build_IsPromotedBuild":true,"Build_BranchName":"++ue5+release-5.4","Build_Changelist":35576357,"Hardware_Platform":"Windows","Hardware_GPU":"","Hardware_CPU":"Intel(R) Core(TM) i5-10400 CPU @ 2.90GHz","Hardware_CPU_Cores_Physical":6,"Hardware_CPU_Cores_Logical":12,"Hardware_RAM":17044029440,"Hardware_ComputerName":"K411","Config_IsEditor":true,"Config_IsUnattended":false,"Config_IsBuildMachine":false,"Config_IsRunningCommandlet":false,"Config_IsDebuggerPresent":false,"MapName":"VRTemplateMap","SchemaVersion":3,"LoadingName":"LoadMap","AssetType":"DistanceField","Load_Count":53,"Load_TimeSec":0.018914,"Load_SizeMB":5.82142,"Build_Count":0,"Build_TimeSec":0.0,"Build_SizeMB":0.0,"Total_Count":53,"Total_TimeSec":0.018914,"Total_SizeMB":5,"Efficiency":1.0,"Thread_TimeSec":0.011532}
{"EventName":"Core.DDC.Resource","TimestampUTC":1730546285.637000,"RecordId":28,"ProjectName":"Kukoverova_Veronika","ProjectID":"00000000000000000000000000000000","Session_ID":"{46A4D377-43C5-81E5-72CD-958C72118432}","Session_Label":"","Session_StartUTC":1730546273.763,"Build_Configuration":"Development","Build_IsInternalBuild":false,"Build_IsPerforceBuild":false,"Build_IsPromotedBuild":true,"Build_BranchName":"++ue5+release-5.4","Build_Changelist":35576357,"Hardware_Platform":"Windows","Hardware_GPU":"","Hardware_CPU":"Intel(R) Core(TM) i5-10400 CPU @ 2.90GHz","Hardware_CPU_Cores_Physical":6,"Hardware_CPU_Cores_Logical":12,"Hardware_RAM":17044029440,"Hardware_ComputerName":"K411","Config_IsEditor":true,"Config_IsUnattended":false,"Config_IsBuildMachine":false,"Config_IsRunningCommandlet":false,"Config_IsDebuggerPresent":false,"MapName":"VRTemplateMap","SchemaVersion":3,"LoadingName":"LoadMap","AssetType":"Audio (Inline)","Load_Count":8,"Load_TimeSec":0.003188,"Load_SizeMB":0.006736,"Build_Count":0,"Build_TimeSec":0.0,"Build_SizeMB":0.0,"Total_Count":8,"Total_TimeSec":0.003188,"Total_SizeMB":0,"Efficiency":1.0,"Thread_TimeSec":0.003188}
{"EventName":"Core.DDC.Resource","TimestampUTC":1730546285.670000,"RecordId":29,"ProjectName":"Kukoverova_Veronika","ProjectID":"00000000000000000000000000000000","Session_ID":"{46A4D377-43C5-81E5-72CD-958C72118432}","Session_Label":"","Session_StartUTC":1730546273.763,"Build_Configuration":"Development","Build_IsInternalBuild":false,"Build_IsPerforceBuild":false,"Build_IsPromotedBuild":true,"Build_BranchName":"++ue5+release-5.4","Build_Changelist":35576357,"Hardware_Platform":"Windows","Hardware_GPU":"","Hardware_CPU":"Intel(R) Core(TM) i5-10400 CPU @ 2.90GHz","Hardware_CPU_Cores_Physical":6,"Hardware_CPU_Cores_Logical":12,"Hardware_RAM":17044029440,"Hardware_ComputerName":"K411","Config_IsEditor":true,"Config_IsUnattended":false,"Config_IsBuildMachine":false,"Config_IsRunningCommandlet":false,"Config_IsDebuggerPresent":false,"MapName":"VRTemplateMap","SchemaVersion":3,"LoadingName":"LoadMap","AssetType":"AnimSequence","Load_Count":5,"Load_TimeSec":0.000162,"Load_SizeMB":0.010886,"Build_Count":0,"Build_TimeSec":0.0,"Build_SizeMB":0.0,"Total_Count":5,"Total_TimeSec":0.000162,"Total_SizeMB":0,"Efficiency":1.0,"Thread_TimeSec":0.0}
{"EventName":"Core.DDC.Resource","TimestampUTC":1730546285.703000,"RecordId":30,"ProjectName":"Kukoverova_Veronika","ProjectID":"00000000000000000000000000000000","Session_ID":"{46A4D377-43C5-81E5-72CD-958C72118432}","Session_Label":"","Session_StartUTC":1730546273.763,"Build_Configuration":"Development","Build_IsInternalBuild":false,"Build_IsPerforceBuild":false,"Build_IsPromotedBuild":true,"Build_BranchName":"++ue5+release-5.4","Build_Changelist":35576357,"Hardware_Platform":"Windows","Hardware_GPU":"","Hardware_CPU":"Intel(R) Core(TM) i5-10400 CPU @ 2.90GHz","Hardware_CPU_Cores_Physical":6,"Hardware_CPU_Cores_Logical":12,"Hardware_RAM":17044029440,"Hardware_ComputerName":"K411","Config_IsEditor":true,"Config_IsUnattended":false,"Config_IsBuildMachine":false,"Config_IsRunningCommandlet":false,"Config_IsDebuggerPresent":false,"MapName":"VRTemplateMap","SchemaVersion":3,"LoadingName":"LoadMap","AssetType":"NavCollision","Load_Count":53,"Load_TimeSec":0.003395,"Load_SizeMB":0.07387,"Build_Count":0,"Build_TimeSec":0.0,"Build_SizeMB":0.0,"Total_Count":53,"Total_TimeSec":0.003395,"Total_SizeMB":0,"Efficiency":1.0,"Thread_TimeSec":0.00191}
{"EventName":"Core.DDC.Resource","TimestampUTC":1730546285.747000,"RecordId":31,"ProjectName":"Kukoverova_Veronika","ProjectID":"00000000000000000000000000000000","Session_ID":"{46A4D377-43C5-81E5-72CD-958C72118432}","Session_Label":"","Session_StartUTC":1730546273.763,"Build_Configuration":"Development","Build_IsInternalBuild":false,"Build_IsPerforceBuild":false,"Build_IsPromotedBuild":true,"Build_BranchName":"++ue5+release-5.4","Build_Changelist":35576357,"Hardware_Platform":"Windows","Hardware_GPU":"","Hardware_CPU":"Intel(R) Core(TM) i5-10400 CPU @ 2.90GHz","Hardware_CPU_Cores_Physical":6,"Hardware_CPU_Cores_Logical":12,"Hardware_RAM":17044029440,"Hardware_ComputerName":"K411","Config_IsEditor":true,"Config_IsUnattended":false,"Config_IsBuildMachine":false,"Config_IsRunningCommandlet":false,"Config_IsDebuggerPresent":false,"MapName":"VRTemplateMap","SchemaVersion":3,"LoadingName":"LoadMap","AssetType":"Total","Load_Count":691,"Load_TimeSec":0.226096,"Load_SizeMB":188.389052,"Build_Count":0,"Build_TimeSec":0.0,"Build_SizeMB":0.0,"Total_Count":691,"Total_TimeSec":0.226096,"Total_SizeMB":188,"Efficiency":1.0,"Thread_TimeSec":0.161547}
{"EventName":"Core.DDC.Summary","TimestampUTC":1730546285.782000,"RecordId":32,"ProjectName":"Kukoverova_Veronika","ProjectID":"00000000000000000000000000000000","Session_ID":"{46A4D377-43C5-81E5-72CD-958C72118432}","Session_Label":"","Session_StartUTC":1730546273.763,"Build_Configuration":"Development","Build_IsInternalBuild":false,"Build_IsPerforceBuild":false,"Build_IsPromotedBuild":true,"Build_BranchName":"++ue5+release-5.4","Build_Changelist":35576357,"Hardware_Platform":"Windows","Hardware_GPU":"","Hardware_CPU":"Intel(R) Core(TM) i5-10400 CPU @ 2.90GHz","Hardware_CPU_Cores_Physical":6,"Hardware_CPU_Cores_Logical":12,"Hardware_RAM":17044029440,"Hardware_ComputerName":"K411","Config_IsEditor":true,"Config_IsUnattended":false,"Config_IsBuildMachine":false,"Config_IsRunningCommandlet":false,"Config_IsDebuggerPresent":false,"MapName":"VRTemplateMap","SchemaVersion":3,"LoadingName":"LoadMap","BackEnd":"InstalledDerivedDataBackendGraph","HasLocalCache":"true","HasSharedCache":"false","HasCloudCache":"false","HasZenCache":"true","TotalGetHits":1171.0,"TotalGetMisses":57.0,"TotalGets":1228.0,"TotalGetHitPct":0.953583,"GetMissPct":0.046417,"TotalPutHits":51.0,"TotalPutMisses":0.0,"TotalPuts":51.0,"TotalPutHitPct":1.0,"PutMissPct":0.0,"LocalGetHits":0.0,"LocalGetTotal":0.0,"LocalGetHitPct":0.0,"SharedGetHits":0.0,"SharedGetTotal":0.0,"SharedGetHitPct":0.0,"ZenLocalGetHits":410.0,"ZenLocalGetTotal":467.0,"ZenLocalGetHitPct":0.877944,"ZenRemoteGetHits":0.0,"ZenRemoteGetTotal":0.0,"ZenRemoteGetHitPct":0.0,"CloudGetHits":0.0,"CloudGetTotal":0.0,"CloudGetHitPct":0.0,"LocalLatency":0.0,"LocalReadSpeed":0.0,"LocalWriteSpeed":0.0,"SharedLatency":0.0,"SharedReadSpeed":0.0,"SharedWriteSpeed":0.0,"CloudLatency":0.0,"CloudReadSpeed":0.0,"CloudWriteSpeed":0.0}
{"EventName":"Core.Zen","TimestampUTC":1730546285.824000,"RecordId":33,"ProjectName":"Kukoverova_Veronika","ProjectID":"00000000000000000000000000000000","Session_ID":"{46A4D377-43C5-81E5-72CD-958C72118432}","Session_Label":"","Session_StartUTC":1730546273.763,"Build_Configuration":"Development","Build_IsInternalBuild":false,"Build_IsPerforceBuild":false,"Build_IsPromotedBuild":true,"Build_BranchName":"++ue5+release-5.4","Build_Changelist":35576357,"Hardware_Platform":"Windows","Hardware_GPU":"","Hardware_CPU":"Intel(R) Core(TM) i5-10400 CPU @ 2.90GHz","Hardware_CPU_Cores_Physical":6,"Hardware_CPU_Cores_Logical":12,"Hardware_RAM":17044029440,"Hardware_ComputerName":"K411","Config_IsEditor":true,"Config_IsUnattended":false,"Config_IsBuildMachine":false,"Config_IsRunningCommandlet":false,"Config_IsDebuggerPresent":false,"MapName":"VRTemplateMap","SchemaVersion":1,"LoadingName":"LoadMap","Zen_Enabled":true,"Zen_Cache_Size_Disk":168329229.0,"Zen_Cache_Size_Memory":70008.0,"Zen_Cache_Hits":459,"Zen_Cache_Misses":6,"Zen_Cache_Writes":51,"Zen_Cache_HitRatio":0.987097,"Zen_Cache_Cas_Hits":600,"Zen_Cache_Cas_Misses":0,"Zen_Cache_Cas_Writes":0,"Zen_Cache_Requests":500,"Zen_Cache_BadRequests":0,"Zen_Cache_Requests_Count":500,"Zen_Cache_Requests_RateMean":49.533314,"Zen_Cache_Requests_TAverage":0.000051,"Zen_Cache_Requests_TMin":0.000013,"Zen_Cache_Requests_TMax":0.000527,"Zen_Cache_TotalUploadedMB":0.0,"Zen_Upstream_TotalDownloadedMB":0.0,"Zen_Upstream_TotalUploadedMB":0.0,"Zen_Upstream_Requests_Count":0,"Zen_Upstream_Requests_RateMean":0.0,"Zen_Upstream_Requests_TAverage":0.0,"Zen_Upstream_Requests_TMin":0.0,"Zen_Upstream_Requests_TMax":0.0,"Zen_Cas_Size_Large":0,"Zen_Cas_Size_Small":182141384,"Zen_Cas_Size_Tiny":132153,"Zen_Cas_Size_Total":182273537,"Zen_Project_Size_Disk":0.0,"Zen_Project_Size_Memory":0.0,"Zen_Project_WriteCount":0,"Zen_Project_ReadCount":0,"Zen_Project_DeleteCount":0,"Zen_Project_Oplog_WriteCount":0,"Zen_Project_Oplog_ReadCount":0,"Zen_Project_Oplog_DeleteCount":0,"Zen_Project_Op_Hits":0,"Zen_Project_Op_Misses":0,"Zen_Project_Op_Writes":0,"Zen_Project_Chunk_Hits":0,"Zen_Project_Chunk_Misses":0,"Zen_Project_Chunk_Writes":0,"Zen_Project_Requests":0,"Zen_Project_BadRequests":0,"Zen_Project_Op_HitRatio":0.0,"Zen_Project_Chunk_HitRatio":0.0}
{"EventName":"Span","TimestampUTC":1730546285.882000,"RecordId":34,"ProjectName":"Kukoverova_Veronika","ProjectID":"00000000000000000000000000000000","Session_ID":"{46A4D377-43C5-81E5-72CD-958C72118432}","Session_Label":"","Session_StartUTC":1730546273.763,"Build_Configuration":"Development","Build_IsInternalBuild":false,"Build_IsPerforceBuild":false,"Build_IsPromotedBuild":true,"Build_BranchName":"++ue5+release-5.4","Build_Changelist":35576357,"Hardware_Platform":"Windows","Hardware_GPU":"","Hardware_CPU":"Intel(R) Core(TM) i5-10400 CPU @ 2.90GHz","Hardware_CPU_Cores_Physical":6,"Hardware_CPU_Cores_Logical":12,"Hardware_RAM":17044029440,"Hardware_ComputerName":"K411","Config_IsEditor":true,"Config_IsUnattended":false,"Config_IsBuildMachine":false,"Config_IsRunningCommandlet":false,"Config_IsDebuggerPresent":false,"MapName":"VRTemplateMap","SchemaVersion":1,"Span_Name":"Editor.Initialize","Span_GUID":"3B0CD5444B7AAB3A4C6096A1DCD9A01A","Span_ParentName":"Editor","Span_ThreadId":10688,"Span_Depth":2,"Span_StartUTC":1730546284.248,"Span_EndUTC":1730546285.882,"Span_TimeInSec":1.634}
{"EventName":"Core.Loading","TimestampUTC":1730546285.949000,"RecordId":35,"ProjectName":"Kukoverova_Veronika","ProjectID":"00000000000000000000000000000000","Session_ID":"{46A4D377-43C5-81E5-72CD-958C72118432}","Session_Label":"","Session_StartUTC":1730546273.763,"Build_Configuration":"Development","Build_IsInternalBuild":false,"Build_IsPerforceBuild":false,"Build_IsPromotedBuild":true,"Build_BranchName":"++ue5+release-5.4","Build_Changelist":35576357,"Hardware_Platform":"Windows","Hardware_GPU":"","Hardware_CPU":"Intel(R) Core(TM) i5-10400 CPU @ 2.90GHz","Hardware_CPU_Cores_Physical":6,"Hardware_CPU_Cores_Logical":12,"Hardware_RAM":17044029440,"Hardware_ComputerName":"K411","Config_IsEditor":true,"Config_IsUnattended":false,"Config_IsBuildMachine":false,"Config_IsRunningCommandlet":false,"Config_IsDebuggerPresent":false,"MapName":"VRTemplateMap","SchemaVersion":3,"LoadingName":"TotalEditorStartup","LoadingSeconds":13.097336,"Zen_Enabled":true,"Zen_Cache_Size_Disk":168329229.0,"Zen_Cache_Size_Memory":70008.0,"Zen_Cache_Hits":459,"Zen_Cache_Misses":6,"Zen_Cache_Writes":51,"Zen_Cache_HitRatio":0.987097,"Zen_Cache_Cas_Hits":600,"Zen_Cache_Cas_Misses":0,"Zen_Cache_Cas_Writes":0,"Zen_Cache_Requests":500,"Zen_Cache_BadRequests":0,"Zen_Cache_Requests_Count":500,"Zen_Cache_Requests_RateMean":49.533314,"Zen_Cache_Requests_TAverage":0.000051,"Zen_Cache_Requests_TMin":0.000013,"Zen_Cache_Requests_TMax":0.000527,"Zen_Cache_TotalUploadedMB":0.0,"Zen_Upstream_TotalDownloadedMB":0.0,"Zen_Upstream_TotalUploadedMB":0.0,"Zen_Upstream_Requests_Count":0,"Zen_Upstream_Requests_RateMean":0.0,"Zen_Upstream_Requests_TAverage":0.0,"Zen_Upstream_Requests_TMin":0.0,"Zen_Upstream_Requests_TMax":0.0,"Zen_Cas_Size_Large":0,"Zen_Cas_Size_Small":182141384,"Zen_Cas_Size_Tiny":132153,"Zen_Cas_Size_Total":182273537,"Zen_Project_Size_Disk":0.0,"Zen_Project_Size_Memory":0.0,"Zen_Project_WriteCount":0,"Zen_Project_ReadCount":0,"Zen_Project_DeleteCount":0,"Zen_Project_Oplog_WriteCount":0,"Zen_Project_Oplog_ReadCount":0,"Zen_Project_Oplog_DeleteCount":0,"Zen_Project_Op_Hits":0,"Zen_Project_Op_Misses":0,"Zen_Project_Op_Writes":0,"Zen_Project_Chunk_Hits":0,"Zen_Project_Chunk_Misses":0,"Zen_Project_Chunk_Writes":0,"Zen_Project_Requests":0,"Zen_Project_BadRequests":0,"Zen_Project_Op_HitRatio":0.0,"Zen_Project_Chunk_HitRatio":0.0,"DDC_Summary_BackEnd":"InstalledDerivedDataBackendGraph","DDC_Summary_HasLocalCache":"true","DDC_Summary_HasSharedCache":"false","DDC_Summary_HasCloudCache":"false","DDC_Summary_HasZenCache":"true","DDC_Summary_TotalGetHits":1171.0,"DDC_Summary_TotalGetMisses":57.0,"DDC_Summary_TotalGets":1228.0,"DDC_Summary_TotalGetHitPct":0.953583,"DDC_Summary_GetMissPct":0.046417,"DDC_Summary_TotalPutHits":51.0,"DDC_Summary_TotalPutMisses":0.0,"DDC_Summary_TotalPuts":51.0,"DDC_Summary_TotalPutHitPct":1.0,"DDC_Summary_PutMissPct":0.0,"DDC_Summary_LocalGetHits":0.0,"DDC_Summary_LocalGetTotal":0.0,"DDC_Summary_LocalGetHitPct":0.0,"DDC_Summary_SharedGetHits":0.0,"DDC_Summary_SharedGetTotal":0.0,"DDC_Summary_SharedGetHitPct":0.0,"DDC_Summary_ZenLocalGetHits":410.0,"DDC_Summary_ZenLocalGetTotal":467.0,"DDC_Summary_ZenLocalGetHitPct":0.877944,"DDC_Summary_ZenRemoteGetHits":0.0,"DDC_Summary_ZenRemoteGetTotal":0.0,"DDC_Summary_ZenRemoteGetHitPct":0.0,"DDC_Summary_CloudGetHits":0.0,"DDC_Summary_CloudGetTotal":0.0,"DDC_Summary_CloudGetHitPct":0.0,"DDC_Summary_LocalLatency":0.0,"DDC_Summary_LocalReadSpeed":0.0,"DDC_Summary_LocalWriteSpeed":0.0,"DDC_Summary_SharedLatency":0.0,"DDC_Summary_SharedReadSpeed":0.0,"DDC_Summary_SharedWriteSpeed":0.0,"DDC_Summary_CloudLatency":0.0,"DDC_Summary_CloudReadSpeed":0.0,"DDC_Summary_CloudWriteSpeed":0.0}
{"EventName":"Core.DDC.Resource","TimestampUTC":1730546285.994000,"RecordId":36,"ProjectName":"Kukoverova_Veronika","ProjectID":"00000000000000000000000000000000","Session_ID":"{46A4D377-43C5-81E5-72CD-958C72118432}","Session_Label":"","Session_StartUTC":1730546273.763,"Build_Configuration":"Development","Build_IsInternalBuild":false,"Build_IsPerforceBuild":false,"Build_IsPromotedBuild":true,"Build_BranchName":"++ue5+release-5.4","Build_Changelist":35576357,"Hardware_Platform":"Windows","Hardware_GPU":"","Hardware_CPU":"Intel(R) Core(TM) i5-10400 CPU @ 2.90GHz","Hardware_CPU_Cores_Physical":6,"Hardware_CPU_Cores_Logical":12,"Hardware_RAM":17044029440,"Hardware_ComputerName":"K411","Config_IsEditor":true,"Config_IsUnattended":false,"Config_IsBuildMachine":false,"Config_IsRunningCommandlet":false,"Config_IsDebuggerPresent":false,"MapName":"VRTemplateMap","SchemaVersion":3,"LoadingName":"TotalEditorStartup","AssetType":"Texture (Inline)","Load_Count":113,"Load_TimeSec":0.022697,"Load_SizeMB":52.509381,"Build_Count":0,"Build_TimeSec":0.0,"Build_SizeMB":0.0,"Total_Count":113,"Total_TimeSec":0.022697,"Total_SizeMB":52,"Efficiency":1.0,"Thread_TimeSec":0.022697}
{"EventName":"Core.DDC.Resource","TimestampUTC":1730546286.026000,"RecordId":37,"ProjectName":"Kukoverova_Veronika","ProjectID":"00000000000000000000000000000000","Session_ID":"{46A4D377-43C5-81E5-72CD-958C72118432}","Session_Label":"","Session_StartUTC":1730546273.763,"Build_Configuration":"Development","Build_IsInternalBuild":false,"Build_IsPerforceBuild":false,"Build_IsPromotedBuild":true,"Build_BranchName":"++ue5+release-5.4","Build_Changelist":35576357,"Hardware_Platform":"Windows","Hardware_GPU":"","Hardware_CPU":"Intel(R) Core(TM) i5-10400 CPU @ 2.90GHz","Hardware_CPU_Cores_Physical":6,"Hardware_CPU_Cores_Logical":12,"Hardware_RAM":17044029440,"Hardware_ComputerName":"K411","Config_IsEditor":true,"Config_IsUnattended":false,"Config_IsBuildMachine":false,"Config_IsRunningCommandlet":false,"Config_IsDebuggerPresent":false,"MapName":"VRTemplateMap","SchemaVersion":3,"LoadingName":"TotalEditorStartup","AssetType":"Texture (Streaming)","Load_Count":30,"Load_TimeSec":0.006572,"Load_SizeMB":8.521484,"Build_Count":0,"Build_TimeSec":0.0,"Build_SizeMB":0.0,"Total_Count":30,"Total_TimeSec":0.006572,"Total_SizeMB":8,"Efficiency":1.0,"Thread_TimeSec":0.006572}
{"EventName":"Core.DDC.Resource","TimestampUTC":1730546286.059000,"RecordId":38,"ProjectName":"Kukoverova_Veronika","ProjectID":"00000000000000000000000000000000","Session_ID":"{46A4D377-43C5-81E5-72CD-958C72118432}","Session_Label":"","Session_StartUTC":1730546273.763,"Build_Configuration":"Development","Build_IsInternalBuild":false,"Build_IsPerforceBuild":false,"Build_IsPromotedBuild":true,"Build_BranchName":"++ue5+release-5.4","Build_Changelist":35576357,"Hardware_Platform":"Windows","Hardware_GPU":"","Hardware_CPU":"Intel(R) Core(TM) i5-10400 CPU @ 2.90GHz","Hardware_CPU_Cores_Physical":6,"Hardware_CPU_Cores_Logical":12,"Hardware_RAM":17044029440,"Hardware_ComputerName":"K411","Config_IsEditor":true,"Config_IsUnattended":false,"Config_IsBuildMachine":false,"Config_IsRunningCommandlet":false,"Config_IsDebuggerPresent":false,"MapName":"VRTemplateMap","SchemaVersion":3,"LoadingName":"TotalEditorStartup","AssetType":"StaticMesh","Load_Count":53,"Load_TimeSec":0.034145,"Load_SizeMB":11.455413,"Build_Count":0,"Build_TimeSec":0.0,"Build_SizeMB":0.0,"Total_Count":53,"Total_TimeSec":0.034145,"Total_SizeMB":11,"Efficiency":1.0,"Thread_TimeSec":0.012337}
{"EventName":"Core.DDC.Resource","TimestampUTC":1730546286.092000,"RecordId":39,"ProjectName":"Kukoverova_Veronika","ProjectID":"00000000000000000000000000000000","Session_ID":"{46A4D377-43C5-81E5-72CD-958C72118432}","Session_Label":"","Session_StartUTC":1730546273.763,"Build_Configuration":"Development","Build_IsInternalBuild":false,"Build_IsPerforceBuild":false,"Build_IsPromotedBuild":true,"Build_BranchName":"++ue5+release-5.4","Build_Changelist":35576357,"Hardware_Platform":"Windows","Hardware_GPU":"","Hardware_CPU":"Intel(R) Core(TM) i5-10400 CPU @ 2.90GHz","Hardware_CPU_Cores_Physical":6,"Hardware_CPU_Cores_Logical":12,"Hardware_RAM":17044029440,"Hardware_ComputerName":"K411","Config_IsEditor":true,"Config_IsUnattended":false,"Config_IsBuildMachine":false,"Config_IsRunningCommandlet":false,"Config_IsDebuggerPresent":false,"MapName":"VRTemplateMap","SchemaVersion":3,"LoadingName":"TotalEditorStartup","AssetType":"SkeletalMesh","Load_Count":3,"Load_TimeSec":0.020559,"Load_SizeMB":4.835098,"Build_Count":0,"Build_TimeSec":0.0,"Build_SizeMB":0.0,"Total_Count":3,"Total_TimeSec":0.020559,"Total_SizeMB":4,"Efficiency":1.0,"Thread_TimeSec":0.0}
{"EventName":"Core.DDC.Resource","TimestampUTC":1730546286.154000,"RecordId":40,"ProjectName":"Kukoverova_Veronika","ProjectID":"00000000000000000000000000000000","Session_ID":"{46A4D377-43C5-81E5-72CD-958C72118432}","Session_Label":"","Session_StartUTC":1730546273.763,"Build_Configuration":"Development","Build_IsInternalBuild":false,"Build_IsPerforceBuild":false,"Build_IsPromotedBuild":true,"Build_BranchName":"++ue5+release-5.4","Build_Changelist":35576357,"Hardware_Platform":"Windows","Hardware_GPU":"","Hardware_CPU":"Intel(R) Core(TM) i5-10400 CPU @ 2.90GHz","Hardware_CPU_Cores_Physical":6,"Hardware_CPU_Cores_Logical":12,"Hardware_RAM":17044029440,"Hardware_ComputerName":"K411","Config_IsEditor":true,"Config_IsUnattended":false,"Config_IsBuildMachine":false,"Config_IsRunningCommandlet":false,"Config_IsDebuggerPresent":false,"MapName":"VRTemplateMap","SchemaVersion":3,"LoadingName":"TotalEditorStartup","AssetType":"GlobalShader","Load_Count":304,"Load_TimeSec":0.083614,"Load_SizeMB":79.224675,"Build_Count":0,"Build_TimeSec":0.0,"Build_SizeMB":0.0,"Total_Count":304,"Total_TimeSec":0.083614,"Total_SizeMB":79,"Efficiency":1.0,"Thread_TimeSec":0.083614}
{"EventName":"Core.DDC.Resource","TimestampUTC":1730546286.181000,"RecordId":41,"ProjectName":"Kukoverova_Veronika","ProjectID":"00000000000000000000000000000000","Session_ID":"{46A4D377-43C5-81E5-72CD-958C72118432}","Session_Label":"","Session_StartUTC":1730546273.763,"Build_Configuration":"Development","Build_IsInternalBuild":false,"Build_IsPerforceBuild":false,"Build_IsPromotedBuild":true,"Build_BranchName":"++ue5+release-5.4","Build_Changelist":35576357,"Hardware_Platform":"Windows","Hardware_GPU":"","Hardware_CPU":"Intel(R) Core(TM) i5-10400 CPU @ 2.90GHz","Hardware_CPU_Cores_Physical":6,"Hardware_CPU_Cores_Logical":12,"Hardware_RAM":17044029440,"Hardware_ComputerName":"K411","Config_IsEditor":true,"Config_IsUnattended":false,"Config_IsBuildMachine":false,"Config_IsRunningCommandlet":false,"Config_IsDebuggerPresent":false,"MapName":"VRTemplateMap","SchemaVersion":3,"LoadingName":"TotalEditorStartup","AssetType":"BodySetup","Load_Count":12,"Load_TimeSec":0.014659,"Load_SizeMB":6.161453,"Build_Count":0,"Build_TimeSec":0.0,"Build_SizeMB":0.0,"Total_Count":12,"Total_TimeSec":0.014659,"Total_SizeMB":6,"Efficiency":1.0,"Thread_TimeSec":0.002488}
{"EventName":"Core.DDC.Resource","TimestampUTC":1730546286.214000,"RecordId":42,"ProjectName":"Kukoverova_Veronika","ProjectID":"00000000000000000000000000000000","Session_ID":"{46A4D377-43C5-81E5-72CD-958C72118432}","Session_Label":"","Session_StartUTC":1730546273.763,"Build_Configuration":"Development","Build_IsInternalBuild":false,"Build_IsPerforceBuild":false,"Build_IsPromotedBuild":true,"Build_BranchName":"++ue5+release-5.4","Build_Changelist":35576357,"Hardware_Platform":"Windows","Hardware_GPU":"","Hardware_CPU":"Intel(R) Core(TM) i5-10400 CPU @ 2.90GHz","Hardware_CPU_Cores_Physical":6,"Hardware_CPU_Cores_Logical":12,"Hardware_RAM":17044029440,"Hardware_ComputerName":"K411","Config_IsEditor":true,"Config_IsUnattended":false,"Config_IsBuildMachine":false,"Config_IsRunningCommandlet":false,"Config_IsDebuggerPresent":false,"MapName":"VRTemplateMap","SchemaVersion":3,"LoadingName":"TotalEditorStartup","AssetType":"CardRepresentation","Load_Count":53,"Load_TimeSec":0.003299,"Load_SizeMB":0.016319,"Build_Count":0,"Build_TimeSec":0.0,"Build_SizeMB":0.0,"Total_Count":53,"Total_TimeSec":0.003299,"Total_SizeMB":0,"Efficiency":1.0,"Thread_TimeSec":0.002317}
{"EventName":"Core.DDC.Resource","TimestampUTC":1730546286.237000,"RecordId":43,"ProjectName":"Kukoverova_Veronika","ProjectID":"00000000000000000000000000000000","Session_ID":"{46A4D377-43C5-81E5-72CD-958C72118432}","Session_Label":"","Session_StartUTC":1730546273.763,"Build_Configuration":"Development","Build_IsInternalBuild":false,"Build_IsPerforceBuild":false,"Build_IsPromotedBuild":true,"Build_BranchName":"++ue5+release-5.4","Build_Changelist":35576357,"Hardware_Platform":"Windows","Hardware_GPU":"","Hardware_CPU":"Intel(R) Core(TM) i5-10400 CPU @ 2.90GHz","Hardware_CPU_Cores_Physical":6,"Hardware_CPU_Cores_Logical":12,"Hardware_RAM":17044029440,"Hardware_ComputerName":"K411","Config_IsEditor":true,"Config_IsUnattended":false,"Config_IsBuildMachine":false,"Config_IsRunningCommandlet":false,"Config_IsDebuggerPresent":false,"MapName":"VRTemplateMap","SchemaVersion":3,"LoadingName":"TotalEditorStartup","AssetType":"MaterialShader","Load_Count":4,"Load_TimeSec":0.014892,"Load_SizeMB":19.752317,"Build_Count":0,"Build_TimeSec":0.0,"Build_SizeMB":0.0,"Total_Count":4,"Total_TimeSec":0.014892,"Total_SizeMB":19,"Efficiency":1.0,"Thread_TimeSec":0.014892}
{"EventName":"Core.DDC.Resource","TimestampUTC":1730546286.258000,"RecordId":44,"ProjectName":"Kukoverova_Veronika","ProjectID":"00000000000000000000000000000000","Session_ID":"{46A4D377-43C5-81E5-72CD-958C72118432}","Session_Label":"","Session_StartUTC":1730546273.763,"Build_Configuration":"Development","Build_IsInternalBuild":false,"Build_IsPerforceBuild":false,"Build_IsPromotedBuild":true,"Build_BranchName":"++ue5+release-5.4","Build_Changelist":35576357,"Hardware_Platform":"Windows","Hardware_GPU":"","Hardware_CPU":"Intel(R) Core(TM) i5-10400 CPU @ 2.90GHz","Hardware_CPU_Cores_Physical":6,"Hardware_CPU_Cores_Logical":12,"Hardware_RAM":17044029440,"Hardware_ComputerName":"K411","Config_IsEditor":true,"Config_IsUnattended":false,"Config_IsBuildMachine":false,"Config_IsRunningCommandlet":false,"Config_IsDebuggerPresent":false,"MapName":"VRTemplateMap","SchemaVersion":3,"LoadingName":"TotalEditorStartup","AssetType":"DistanceField","Load_Count":53,"Load_TimeSec":0.018914,"Load_SizeMB":5.82142,"Build_Count":0,"Build_TimeSec":0.0,"Build_SizeMB":0.0,"Total_Count":53,"Total_TimeSec":0.018914,"Total_SizeMB":5,"Efficiency":1.0,"Thread_TimeSec":0.011532}
{"EventName":"Core.DDC.Resource","TimestampUTC":1730546286.281000,"RecordId":45,"ProjectName":"Kukoverova_Veronika","ProjectID":"00000000000000000000000000000000","Session_ID":"{46A4D377-43C5-81E5-72CD-958C72118432}","Session_Label":"","Session_StartUTC":1730546273.763,"Build_Configuration":"Development","Build_IsInternalBuild":false,"Build_IsPerforceBuild":false,"Build_IsPromotedBuild":true,"Build_BranchName":"++ue5+release-5.4","Build_Changelist":35576357,"Hardware_Platform":"Windows","Hardware_GPU":"","Hardware_CPU":"Intel(R) Core(TM) i5-10400 CPU @ 2.90GHz","Hardware_CPU_Cores_Physical":6,"Hardware_CPU_Cores_Logical":12,"Hardware_RAM":17044029440,"Hardware_ComputerName":"K411","Config_IsEditor":true,"Config_IsUnattended":false,"Config_IsBuildMachine":false,"Config_IsRunningCommandlet":false,"Config_IsDebuggerPresent":false,"MapName":"VRTemplateMap","SchemaVersion":3,"LoadingName":"TotalEditorStartup","AssetType":"Audio (Inline)","Load_Count":8,"Load_TimeSec":0.003188,"Load_SizeMB":0.006736,"Build_Count":0,"Build_TimeSec":0.0,"Build_SizeMB":0.0,"Total_Count":8,"Total_TimeSec":0.003188,"Total_SizeMB":0,"Efficiency":1.0,"Thread_TimeSec":0.003188}
{"EventName":"Core.DDC.Resource","TimestampUTC":1730546286.303000,"RecordId":46,"ProjectName":"Kukoverova_Veronika","ProjectID":"00000000000000000000000000000000","Session_ID":"{46A4D377-43C5-81E5-72CD-958C72118432}","Session_Label":"","Session_StartUTC":1730546273.763,"Build_Configuration":"Development","Build_IsInternalBuild":false,"Build_IsPerforceBuild":false,"Build_IsPromotedBuild":true,"Build_BranchName":"++ue5+release-5.4","Build_Changelist":35576357,"Hardware_Platform":"Windows","Hardware_GPU":"","Hardware_CPU":"Intel(R) Core(TM) i5-10400 CPU @ 2.90GHz","Hardware_CPU_Cores_Physical":6,"Hardware_CPU_Cores_Logical":12,"Hardware_RAM":17044029440,"Hardware_ComputerName":"K411","Config_IsEditor":true,"Config_IsUnattended":false,"Config_IsBuildMachine":false,"Config_IsRunningCommandlet":false,"Config_IsDebuggerPresent":false,"MapName":"VRTemplateMap","SchemaVersion":3,"LoadingName":"TotalEditorStartup","AssetType":"AnimSequence","Load_Count":5,"Load_TimeSec":0.000162,"Load_SizeMB":0.010886,"Build_Count":0,"Build_TimeSec":0.0,"Build_SizeMB":0.0,"Total_Count":5,"Total_TimeSec":0.000162,"Total_SizeMB":0,"Efficiency":1.0,"Thread_TimeSec":0.0}
{"EventName":"Core.DDC.Resource","TimestampUTC":1730546286.326000,"RecordId":47,"ProjectName":"Kukoverova_Veronika","ProjectID":"00000000000000000000000000000000","Session_ID":"{46A4D377-43C5-81E5-72CD-958C72118432}","Session_Label":"","Session_StartUTC":1730546273.763,"Build_Configuration":"Development","Build_IsInternalBuild":false,"Build_IsPerforceBuild":false,"Build_IsPromotedBuild":true,"Build_BranchName":"++ue5+release-5.4","Build_Changelist":35576357,"Hardware_Platform":"Windows","Hardware_GPU":"","Hardware_CPU":"Intel(R) Core(TM) i5-10400 CPU @ 2.90GHz","Hardware_CPU_Cores_Physical":6,"Hardware_CPU_Cores_Logical":12,"Hardware_RAM":17044029440,"Hardware_ComputerName":"K411","Config_IsEditor":true,"Config_IsUnattended":false,"Config_IsBuildMachine":false,"Config_IsRunningCommandlet":false,"Config_IsDebuggerPresent":false,"MapName":"VRTemplateMap","SchemaVersion":3,"LoadingName":"TotalEditorStartup","AssetType":"NavCollision","Load_Count":53,"Load_TimeSec":0.003395,"Load_SizeMB":0.07387,"Build_Count":0,"Build_TimeSec":0.0,"Build_SizeMB":0.0,"Total_Count":53,"Total_TimeSec":0.003395,"Total_SizeMB":0,"Efficiency":1.0,"Thread_TimeSec":0.00191}
{"EventName":"Core.DDC.Resource","TimestampUTC":1730546286.359000,"RecordId":48,"ProjectName":"Kukoverova_Veronika","ProjectID":"00000000000000000000000000000000","Session_ID":"{46A4D377-43C5-81E5-72CD-958C72118432}","Session_Label":"","Session_StartUTC":1730546273.763,"Build_Configuration":"Development","Build_IsInternalBuild":false,"Build_IsPerforceBuild":false,"Build_IsPromotedBuild":true,"Build_BranchName":"++ue5+release-5.4","Build_Changelist":35576357,"Hardware_Platform":"Windows","Hardware_GPU":"","Hardware_CPU":"Intel(R) Core(TM) i5-10400 CPU @ 2.90GHz","Hardware_CPU_Cores_Physical":6,"Hardware_CPU_Cores_Logical":12,"Hardware_RAM":17044029440,"Hardware_ComputerName":"K411","Config_IsEditor":true,"Config_IsUnattended":false,"Config_IsBuildMachine":false,"Config_IsRunningCommandlet":false,"Config_IsDebuggerPresent":false,"MapName":"VRTemplateMap","SchemaVersion":3,"LoadingName":"TotalEditorStartup","AssetType":"Total","Load_Count":691,"Load_TimeSec":0.226096,"Load_SizeMB":188.389052,"Build_Count":0,"Build_TimeSec":0.0,"Build_SizeMB":0.0,"Total_Count":691,"Total_TimeSec":0.226096,"Total_SizeMB":188,"Efficiency":1.0,"Thread_TimeSec":0.161547}
{"EventName":"Core.DDC.Summary","TimestampUTC":1730546286.393000,"RecordId":49,"ProjectName":"Kukoverova_Veronika","ProjectID":"00000000000000000000000000000000","Session_ID":"{46A4D377-43C5-81E5-72CD-958C72118432}","Session_Label":"","Session_StartUTC":1730546273.763,"Build_Configuration":"Development","Build_IsInternalBuild":false,"Build_IsPerforceBuild":false,"Build_IsPromotedBuild":true,"Build_BranchName":"++ue5+release-5.4","Build_Changelist":35576357,"Hardware_Platform":"Windows","Hardware_GPU":"","Hardware_CPU":"Intel(R) Core(TM) i5-10400 CPU @ 2.90GHz","Hardware_CPU_Cores_Physical":6,"Hardware_CPU_Cores_Logical":12,"Hardware_RAM":17044029440,"Hardware_ComputerName":"K411","Config_IsEditor":true,"Config_IsUnattended":false,"Config_IsBuildMachine":false,"Config_IsRunningCommandlet":false,"Config_IsDebuggerPresent":false,"MapName":"VRTemplateMap","SchemaVersion":3,"LoadingName":"TotalEditorStartup","BackEnd":"InstalledDerivedDataBackendGraph","HasLocalCache":"true","HasSharedCache":"false","HasCloudCache":"false","HasZenCache":"true","TotalGetHits":1171.0,"TotalGetMisses":57.0,"TotalGets":1228.0,"TotalGetHitPct":0.953583,"GetMissPct":0.046417,"TotalPutHits":51.0,"TotalPutMisses":0.0,"TotalPuts":51.0,"TotalPutHitPct":1.0,"PutMissPct":0.0,"LocalGetHits":0.0,"LocalGetTotal":0.0,"LocalGetHitPct":0.0,"SharedGetHits":0.0,"SharedGetTotal":0.0,"SharedGetHitPct":0.0,"ZenLocalGetHits":410.0,"ZenLocalGetTotal":467.0,"ZenLocalGetHitPct":0.877944,"ZenRemoteGetHits":0.0,"ZenRemoteGetTotal":0.0,"ZenRemoteGetHitPct":0.0,"CloudGetHits":0.0,"CloudGetTotal":0.0,"CloudGetHitPct":0.0,"LocalLatency":0.0,"LocalReadSpeed":0.0,"LocalWriteSpeed":0.0,"SharedLatency":0.0,"SharedReadSpeed":0.0,"SharedWriteSpeed":0.0,"CloudLatency":0.0,"CloudReadSpeed":0.0,"CloudWriteSpeed":0.0}
{"EventName":"Core.Zen","TimestampUTC":1730546286.426000,"RecordId":50,"ProjectName":"Kukoverova_Veronika","ProjectID":"00000000000000000000000000000000","Session_ID":"{46A4D377-43C5-81E5-72CD-958C72118432}","Session_Label":"","Session_StartUTC":1730546273.763,"Build_Configuration":"Development","Build_IsInternalBuild":false,"Build_IsPerforceBuild":false,"Build_IsPromotedBuild":true,"Build_BranchName":"++ue5+release-5.4","Build_Changelist":35576357,"Hardware_Platform":"Windows","Hardware_GPU":"","Hardware_CPU":"Intel(R) Core(TM) i5-10400 CPU @ 2.90GHz","Hardware_CPU_Cores_Physical":6,"Hardware_CPU_Cores_Logical":12,"Hardware_RAM":17044029440,"Hardware_ComputerName":"K411","Config_IsEditor":true,"Config_IsUnattended":false,"Config_IsBuildMachine":false,"Config_IsRunningCommandlet":false,"Config_IsDebuggerPresent":false,"MapName":"VRTemplateMap","SchemaVersion":1,"LoadingName":"TotalEditorStartup","Zen_Enabled":true,"Zen_Cache_Size_Disk":168329229.0,"Zen_Cache_Size_Memory":70008.0,"Zen_Cache_Hits":459,"Zen_Cache_Misses":6,"Zen_Cache_Writes":51,"Zen_Cache_HitRatio":0.987097,"Zen_Cache_Cas_Hits":600,"Zen_Cache_Cas_Misses":0,"Zen_Cache_Cas_Writes":0,"Zen_Cache_Requests":500,"Zen_Cache_BadRequests":0,"Zen_Cache_Requests_Count":500,"Zen_Cache_Requests_RateMean":49.533314,"Zen_Cache_Requests_TAverage":0.000051,"Zen_Cache_Requests_TMin":0.000013,"Zen_Cache_Requests_TMax":0.000527,"Zen_Cache_TotalUploadedMB":0.0,"Zen_Upstream_TotalDownloadedMB":0.0,"Zen_Upstream_TotalUploadedMB":0.0,"Zen_Upstream_Requests_Count":0,"Zen_Upstream_Requests_RateMean":0.0,"Zen_Upstream_Requests_TAverage":0.0,"Zen_Upstream_Requests_TMin":0.0,"Zen_Upstream_Requests_TMax":0.0,"Zen_Cas_Size_Large":0,"Zen_Cas_Size_Small":182141384,"Zen_Cas_Size_Tiny":132153,"Zen_Cas_Size_Total":182273537,"Zen_Project_Size_Disk":0.0,"Zen_Project_Size_Memory":0.0,"Zen_Project_WriteCount":0,"Zen_Project_ReadCount":0,"Zen_Project_DeleteCount":0,"Zen_Project_Oplog_WriteCount":0,"Zen_Project_Oplog_ReadCount":0,"Zen_Project_Oplog_DeleteCount":0,"Zen_Project_Op_Hits":0,"Zen_Project_Op_Misses":0,"Zen_Project_Op_Writes":0,"Zen_Project_Chunk_Hits":0,"Zen_Project_Chunk_Misses":0,"Zen_Project_Chunk_Writes":0,"Zen_Project_Requests":0,"Zen_Project_BadRequests":0,"Zen_Project_Op_HitRatio":0.0,"Zen_Project_Chunk_HitRatio":0.0}
{"EventName":"Editor.AssetRegistry.InitialScan","TimestampUTC":1730546287.652000,"RecordId":51,"ProjectName":"Kukoverova_Veronika","ProjectID":"00000000000000000000000000000000","Session_ID":"{46A4D377-43C5-81E5-72CD-958C72118432}","Session_Label":"","Session_StartUTC":1730546273.763,"Build_Configuration":"Development","Build_IsInternalBuild":false,"Build_IsPerforceBuild":false,"Build_IsPromotedBuild":true,"Build_BranchName":"++ue5+release-5.4","Build_Changelist":35576357,"Hardware_Platform":"Windows","Hardware_GPU":"","Hardware_CPU":"Intel(R) Core(TM) i5-10400 CPU @ 2.90GHz","Hardware_CPU_Cores_Physical":6,"Hardware_CPU_Cores_Logical":12,"Hardware_RAM":17044029440,"Hardware_ComputerName":"K411","Config_IsEditor":true,"Config_IsUnattended":false,"Config_IsBuildMachine":false,"Config_IsRunningCommandlet":false,"Config_IsDebuggerPresent":false,"SchemaVersion":1,"TotalDurationSeconds":9.199354,"TotalWorkSeconds":0.092984,"DiscoverySeconds":0.027077,"GatherSeconds":0.017654,"StoreSeconds":0.048254,"NumCachedDirectories":0,"NumUncachedDirectories":1381,"NumCachedAssetFiles":7236,"NumUncachedAssetFiles":2}
{"EventName":"Span","TimestampUTC":1730546288.795000,"RecordId":52,"ProjectName":"Kukoverova_Veronika","ProjectID":"00000000000000000000000000000000","Session_ID":"{46A4D377-43C5-81E5-72CD-958C72118432}","Session_Label":"","Session_StartUTC":1730546273.763,"Build_Configuration":"Development","Build_IsInternalBuild":false,"Build_IsPerforceBuild":false,"Build_IsPromotedBuild":true,"Build_BranchName":"++ue5+release-5.4","Build_Changelist":35576357,"Hardware_Platform":"Windows","Hardware_GPU":"","Hardware_CPU":"Intel(R) Core(TM) i5-10400 CPU @ 2.90GHz","Hardware_CPU_Cores_Physical":6,"Hardware_CPU_Cores_Logical":12,"Hardware_RAM":17044029440,"Hardware_ComputerName":"K411","Config_IsEditor":true,"Config_IsUnattended":false,"Config_IsBuildMachine":false,"Config_IsRunningCommandlet":false,"Config_IsDebuggerPresent":false,"Hitch_Count":2,"Hitch_HitchesPerSecond":null,"Hitch_AverageFPS":119.916336,"SchemaVersion":1,"Span_Name":"Hitching","Span_GUID":"8B5990D24B60C0B2AA6FD5A62A9C6876","Span_ParentName":"Editor.Interact","Span_ThreadId":10688,"Span_Depth":3,"Span_StartUTC":1730546287.862,"Span_EndUTC":1730546288.795,"Span_TimeInSec":0.933}
{"EventName":"Span","TimestampUTC":1730546288.836000,"RecordId":53,"ProjectName":"Kukoverova_Veronika","ProjectID":"00000000000000000000000000000000","Session_ID":"{46A4D377-43C5-81E5-72CD-958C72118432}","Session_Label":"","Session_StartUTC":1730546273.763,"Build_Configuration":"Development","Build_IsInternalBuild":false,"Build_IsPerforceBuild":false,"Build_IsPromotedBuild":true,"Build_BranchName":"++ue5+release-5.4","Build_Changelist":35576357,"Hardware_Platform":"Windows","Hardware_GPU":"","Hardware_CPU":"Intel(R) Core(TM) i5-10400 CPU @ 2.90GHz","Hardware_CPU_Cores_Physical":6,"Hardware_CPU_Cores_Logical":12,"Hardware_RAM":17044029440,"Hardware_ComputerName":"K411","Config_IsEditor":true,"Config_IsUnattended":false,"Config_IsBuildMachine":false,"Config_IsRunningCommandlet":false,"Config_IsDebuggerPresent":false,"Hitch_Count":2,"Hitch_HitchesPerSecond":null,"Hitch_AverageFPS":119.916336,"SchemaVersion":1,"Span_Name":"Asset Registry Scan","Span_GUID":"F83E169E46C6B6DC6EC33293A7093F06","Span_ParentName":"Hitching","Span_ThreadId":10688,"Span_Depth":4,"Span_StartUTC":1730546287.862,"Span_EndUTC":1730546288.836,"Span_TimeInSec":0.974}
{"EventName":"Core.Hitch","TimestampUTC":1730546288.849000,"RecordId":54,"ProjectName":"Kukoverova_Veronika","ProjectID":"00000000000000000000000000000000","Session_ID":"{46A4D377-43C5-81E5-72CD-958C72118432}","Session_Label":"","Session_StartUTC":1730546273.763,"Build_Configuration":"Development","Build_IsInternalBuild":false,"Build_IsPerforceBuild":false,"Build_IsPromotedBuild":true,"Build_BranchName":"++ue5+release-5.4","Build_Changelist":35576357,"Hardware_Platform":"Windows","Hardware_GPU":"","Hardware_CPU":"Intel(R) Core(TM) i5-10400 CPU @ 2.90GHz","Hardware_CPU_Cores_Physical":6,"Hardware_CPU_Cores_Logical":12,"Hardware_RAM":17044029440,"Hardware_ComputerName":"K411","Config_IsEditor":true,"Config_IsUnattended":false,"Config_IsBuildMachine":false,"Config_IsRunningCommandlet":false,"Config_IsDebuggerPresent":false,"Hitch_Count":2,"Hitch_HitchesPerSecond":null,"Hitch_AverageFPS":119.916336}
{"EventName":"Core.DDC.Resource","TimestampUTC":1730546288.871000,"RecordId":55,"ProjectName":"Kukoverova_Veronika","ProjectID":"00000000000000000000000000000000","Session_ID":"{46A4D377-43C5-81E5-72CD-958C72118432}","Session_Label":"","Session_StartUTC":1730546273.763,"Build_Configuration":"Development","Build_IsInternalBuild":false,"Build_IsPerforceBuild":false,"Build_IsPromotedBuild":true,"Build_BranchName":"++ue5+release-5.4","Build_Changelist":35576357,"Hardware_Platform":"Windows","Hardware_GPU":"","Hardware_CPU":"Intel(R) Core(TM) i5-10400 CPU @ 2.90GHz","Hardware_CPU_Cores_Physical":6,"Hardware_CPU_Cores_Logical":12,"Hardware_RAM":17044029440,"Hardware_ComputerName":"K411","Config_IsEditor":true,"Config_IsUnattended":false,"Config_IsBuildMachine":false,"Config_IsRunningCommandlet":false,"Config_IsDebuggerPresent":false,"SchemaVersion":3,"LoadingName":"Hitch","AssetType":"Texture (Inline)","Load_Count":213,"Load_TimeSec":0.022904,"Load_SizeMB":90.526174,"Build_Count":0,"Build_TimeSec":0.0,"Build_SizeMB":0.0,"Total_Count":213,"Total_TimeSec":0.022904,"Total_SizeMB":90,"Efficiency":1.0,"Thread_TimeSec":0.022904}
{"EventName":"Core.DDC.Resource","TimestampUTC":1730546288.883000,"RecordId":56,"ProjectName":"Kukoverova_Veronika","ProjectID":"00000000000000000000000000000000","Session_ID":"{46A4D377-43C5-81E5-72CD-958C72118432}","Session_Label":"","Session_StartUTC":1730546273.763,"Build_Configuration":"Development","Build_IsInternalBuild":false,"Build_IsPerforceBuild":false,"Build_IsPromotedBuild":true,"Build_BranchName":"++ue5+release-5.4","Build_Changelist":35576357,"Hardware_Platform":"Windows","Hardware_GPU":"","Hardware_CPU":"Intel(R) Core(TM) i5-10400 CPU @ 2.90GHz","Hardware_CPU_Cores_Physical":6,"Hardware_CPU_Cores_Logical":12,"Hardware_RAM":17044029440,"Hardware_ComputerName":"K411","Config_IsEditor":true,"Config_IsUnattended":false,"Config_IsBuildMachine":false,"Config_IsRunningCommandlet":false,"Config_IsDebuggerPresent":false,"SchemaVersion":3,"LoadingName":"Hitch","AssetType":"Texture (Streaming)","Load_Count":35,"Load_TimeSec":0.008238,"Load_SizeMB":10.817871,"Build_Count":0,"Build_TimeSec":0.0,"Build_SizeMB":0.0,"Total_Count":35,"Total_TimeSec":0.008238,"Total_SizeMB":10,"Efficiency":1.0,"Thread_TimeSec":0.008238}
{"EventName":"Core.DDC.Resource","TimestampUTC":1730546288.903000,"RecordId":57,"ProjectName":"Kukoverova_Veronika","ProjectID":"00000000000000000000000000000000","Session_ID":"{46A4D377-43C5-81E5-72CD-958C72118432}","Session_Label":"","Session_StartUTC":1730546273.763,"Build_Configuration":"Development","Build_IsInternalBuild":false,"Build_IsPerforceBuild":false,"Build_IsPromotedBuild":true,"Build_BranchName":"++ue5+release-5.4","Build_Changelist":35576357,"Hardware_Platform":"Windows","Hardware_GPU":"","Hardware_CPU":"Intel(R) Core(TM) i5-10400 CPU @ 2.90GHz","Hardware_CPU_Cores_Physical":6,"Hardware_CPU_Cores_Logical":12,"Hardware_RAM":17044029440,"Hardware_ComputerName":"K411","Config_IsEditor":true,"Config_IsUnattended":false,"Config_IsBuildMachine":false,"Config_IsRunningCommandlet":false,"Config_IsDebuggerPresent":false,"SchemaVersion":3,"LoadingName":"Hitch","AssetType":"StaticMesh","Load_Count":53,"Load_TimeSec":0.034145,"Load_SizeMB":11.455413,"Build_Count":0,"Build_TimeSec":0.0,"Build_SizeMB":0.0,"Total_Count":53,"Total_TimeSec":0.034145,"Total_SizeMB":11,"Efficiency":1.0,"Thread_TimeSec":0.012337}
{"EventName":"Core.DDC.Resource","TimestampUTC":1730546289.013000,"RecordId":58,"ProjectName":"Kukoverova_Veronika","ProjectID":"00000000000000000000000000000000","Session_ID":"{46A4D377-43C5-81E5-72CD-958C72118432}","Session_Label":"","Session_StartUTC":1730546273.763,"Build_Configuration":"Development","Build_IsInternalBuild":false,"Build_IsPerforceBuild":false,"Build_IsPromotedBuild":true,"Build_BranchName":"++ue5+release-5.4","Build_Changelist":35576357,"Hardware_Platform":"Windows","Hardware_GPU":"","Hardware_CPU":"Intel(R) Core(TM) i5-10400 CPU @ 2.90GHz","Hardware_CPU_Cores_Physical":6,"Hardware_CPU_Cores_Logical":12,"Hardware_RAM":17044029440,"Hardware_ComputerName":"K411","Config_IsEditor":true,"Config_IsUnattended":false,"Config_IsBuildMachine":false,"Config_IsRunningCommandlet":false,"Config_IsDebuggerPresent":false,"SchemaVersion":3,"LoadingName":"Hitch","AssetType":"SkeletalMesh","Load_Count":3,"Load_TimeSec":0.020559,"Load_SizeMB":4.835098,"Build_Count":0,"Build_TimeSec":0.0,"Build_SizeMB":0.0,"Total_Count":3,"Total_TimeSec":0.020559,"Total_SizeMB":4,"Efficiency":1.0,"Thread_TimeSec":0.0}
{"EventName":"Core.DDC.Resource","TimestampUTC":1730546289.048000,"RecordId":59,"ProjectName":"Kukoverova_Veronika","ProjectID":"00000000000000000000000000000000","Session_ID":"{46A4D377-43C5-81E5-72CD-958C72118432}","Session_Label":"","Session_StartUTC":1730546273.763,"Build_Configuration":"Development","Build_IsInternalBuild":false,"Build_IsPerforceBuild":false,"Build_IsPromotedBuild":true,"Build_BranchName":"++ue5+release-5.4","Build_Changelist":35576357,"Hardware_Platform":"Windows","Hardware_GPU":"","Hardware_CPU":"Intel(R) Core(TM) i5-10400 CPU @ 2.90GHz","Hardware_CPU_Cores_Physical":6,"Hardware_CPU_Cores_Logical":12,"Hardware_RAM":17044029440,"Hardware_ComputerName":"K411","Config_IsEditor":true,"Config_IsUnattended":false,"Config_IsBuildMachine":false,"Config_IsRunningCommandlet":false,"Config_IsDebuggerPresent":false,"SchemaVersion":3,"LoadingName":"Hitch","AssetType":"GlobalShader","Load_Count":304,"Load_TimeSec":0.083614,"Load_SizeMB":79.224675,"Build_Count":0,"Build_TimeSec":0.0,"Build_SizeMB":0.0,"Total_Count":304,"Total_TimeSec":0.083614,"Total_SizeMB":79,"Efficiency":1.0,"Thread_TimeSec":0.083614}
{"EventName":"Core.DDC.Resource","TimestampUTC":1730546289.071000,"RecordId":60,"ProjectName":"Kukoverova_Veronika","ProjectID":"00000000000000000000000000000000","Session_ID":"{46A4D377-43C5-81E5-72CD-958C72118432}","Session_Label":"","Session_StartUTC":1730546273.763,"Build_Configuration":"Development","Build_IsInternalBuild":false,"Build_IsPerforceBuild":false,"Build_IsPromotedBuild":true,"Build_BranchName":"++ue5+release-5.4","Build_Changelist":35576357,"Hardware_Platform":"Windows","Hardware_GPU":"","Hardware_CPU":"Intel(R) Core(TM) i5-10400 CPU @ 2.90GHz","Hardware_CPU_Cores_Physical":6,"Hardware_CPU_Cores_Logical":12,"Hardware_RAM":17044029440,"Hardware_ComputerName":"K411","Config_IsEditor":true,"Config_IsUnattended":false,"Config_IsBuildMachine":false,"Config_IsRunningCommandlet":false,"Config_IsDebuggerPresent":false,"SchemaVersion":3,"LoadingName":"Hitch","AssetType":"BodySetup","Load_Count":12,"Load_TimeSec":0.014659,"Load_SizeMB":6.161453,"Build_Count":0,"Build_TimeSec":0.0,"Build_SizeMB":0.0,"Total_Count":12,"Total_TimeSec":0.014659,"Total_SizeMB":6,"Efficiency":1.0,"Thread_TimeSec":0.002488}
{"EventName":"Core.DDC.Resource","TimestampUTC":1730546289.103000,"RecordId":61,"ProjectName":"Kukoverova_Veronika","ProjectID":"00000000000000000000000000000000","Session_ID":"{46A4D377-43C5-81E5-72CD-958C72118432}","Session_Label":"","Session_StartUTC":1730546273.763,"Build_Configuration":"Development","Build_IsInternalBuild":false,"Build_IsPerforceBuild":false,"Build_IsPromotedBuild":true,"Build_BranchName":"++ue5+release-5.4","Build_Changelist":35576357,"Hardware_Platform":"Windows","Hardware_GPU":"","Hardware_CPU":"Intel(R) Core(TM) i5-10400 CPU @ 2.90GHz","Hardware_CPU_Cores_Physical":6,"Hardware_CPU_Cores_Logical":12,"Hardware_RAM":17044029440,"Hardware_ComputerName":"K411","Config_IsEditor":true,"Config_IsUnattended":false,"Config_IsBuildMachine":false,"Config_IsRunningCommandlet":false,"Config_IsDebuggerPresent":false,"SchemaVersion":3,"LoadingName":"Hitch","AssetType":"CardRepresentation","Load_Count":53,"Load_TimeSec":0.003299,"Load_SizeMB":0.016319,"Build_Count":0,"Build_TimeSec":0.0,"Build_SizeMB":0.0,"Total_Count":53,"Total_TimeSec":0.003299,"Total_SizeMB":0,"Efficiency":1.0,"Thread_TimeSec":0.002317}
{"EventName":"Core.DDC.Resource","TimestampUTC":1730546289.126000,"RecordId":62,"ProjectName":"Kukoverova_Veronika","ProjectID":"00000000000000000000000000000000","Session_ID":"{46A4D377-43C5-81E5-72CD-958C72118432}","Session_Label":"","Session_StartUTC":1730546273.763,"Build_Configuration":"Development","Build_IsInternalBuild":false,"Build_IsPerforceBuild":false,"Build_IsPromotedBuild":true,"Build_BranchName":"++ue5+release-5.4","Build_Changelist":35576357,"Hardware_Platform":"Windows","Hardware_GPU":"","Hardware_CPU":"Intel(R) Core(TM) i5-10400 CPU @ 2.90GHz","Hardware_CPU_Cores_Physical":6,"Hardware_CPU_Cores_Logical":12,"Hardware_RAM":17044029440,"Hardware_ComputerName":"K411","Config_IsEditor":true,"Config_IsUnattended":false,"Config_IsBuildMachine":false,"Config_IsRunningCommandlet":false,"Config_IsDebuggerPresent":false,"SchemaVersion":3,"LoadingName":"Hitch","AssetType":"MaterialShader","Load_Count":4,"Load_TimeSec":0.014892,"Load_SizeMB":19.752317,"Build_Count":0,"Build_TimeSec":0.0,"Build_SizeMB":0.0,"Total_Count":4,"Total_TimeSec":0.014892,"Total_SizeMB":19,"Efficiency":1.0,"Thread_TimeSec":0.014892}
{"EventName":"Core.DDC.Resource","TimestampUTC":1730546289.159000,"RecordId":63,"ProjectName":"Kukoverova_Veronika","ProjectID":"00000000000000000000000000000000","Session_ID":"{46A4D377-43C5-81E5-72CD-958C72118432}","Session_Label":"","Session_StartUTC":1730546273.763,"Build_Configuration":"Development","Build_IsInternalBuild":false,"Build_IsPerforceBuild":false,"Build_IsPromotedBuild":true,"Build_BranchName":"++ue5+release-5.4","Build_Changelist":35576357,"Hardware_Platform":"Windows","Hardware_GPU":"","Hardware_CPU":"Intel(R) Core(TM) i5-10400 CPU @ 2.90GHz","Hardware_CPU_Cores_Physical":6,"Hardware_CPU_Cores_Logical":12,"Hardware_RAM":17044029440,"Hardware_ComputerName":"K411","Config_IsEditor":true,"Config_IsUnattended":false,"Config_IsBuildMachine":false,"Config_IsRunningCommandlet":false,"Config_IsDebuggerPresent":false,"SchemaVersion":3,"LoadingName":"Hitch","AssetType":"DistanceField","Load_Count":53,"Load_TimeSec":0.018914,"Load_SizeMB":5.82142,"Build_Count":0,"Build_TimeSec":0.0,"Build_SizeMB":0.0,"Total_Count":53,"Total_TimeSec":0.018914,"Total_SizeMB":5,"Efficiency":1.0,"Thread_TimeSec":0.011532}
{"EventName":"Core.DDC.Resource","TimestampUTC":1730546289.285000,"RecordId":64,"ProjectName":"Kukoverova_Veronika","ProjectID":"00000000000000000000000000000000","Session_ID":"{46A4D377-43C5-81E5-72CD-958C72118432}","Session_Label":"","Session_StartUTC":1730546273.763,"Build_Configuration":"Development","Build_IsInternalBuild":false,"Build_IsPerforceBuild":false,"Build_IsPromotedBuild":true,"Build_BranchName":"++ue5+release-5.4","Build_Changelist":35576357,"Hardware_Platform":"Windows","Hardware_GPU":"","Hardware_CPU":"Intel(R) Core(TM) i5-10400 CPU @ 2.90GHz","Hardware_CPU_Cores_Physical":6,"Hardware_CPU_Cores_Logical":12,"Hardware_RAM":17044029440,"Hardware_ComputerName":"K411","Config_IsEditor":true,"Config_IsUnattended":false,"Config_IsBuildMachine":false,"Config_IsRunningCommandlet":false,"Config_IsDebuggerPresent":false,"SchemaVersion":3,"LoadingName":"Hitch","AssetType":"Audio (Inline)","Load_Count":8,"Load_TimeSec":0.003188,"Load_SizeMB":0.006736,"Build_Count":0,"Build_TimeSec":0.0,"Build_SizeMB":0.0,"Total_Count":8,"Total_TimeSec":0.003188,"Total_SizeMB":0,"Efficiency":1.0,"Thread_TimeSec":0.003188}
{"EventName":"Core.DDC.Resource","TimestampUTC":1730546289.314000,"RecordId":65,"ProjectName":"Kukoverova_Veronika","ProjectID":"00000000000000000000000000000000","Session_ID":"{46A4D377-43C5-81E5-72CD-958C72118432}","Session_Label":"","Session_StartUTC":1730546273.763,"Build_Configuration":"Development","Build_IsInternalBuild":false,"Build_IsPerforceBuild":false,"Build_IsPromotedBuild":true,"Build_BranchName":"++ue5+release-5.4","Build_Changelist":35576357,"Hardware_Platform":"Windows","Hardware_GPU":"","Hardware_CPU":"Intel(R) Core(TM) i5-10400 CPU @ 2.90GHz","Hardware_CPU_Cores_Physical":6,"Hardware_CPU_Cores_Logical":12,"Hardware_RAM":17044029440,"Hardware_ComputerName":"K411","Config_IsEditor":true,"Config_IsUnattended":false,"Config_IsBuildMachine":false,"Config_IsRunningCommandlet":false,"Config_IsDebuggerPresent":false,"SchemaVersion":3,"LoadingName":"Hitch","AssetType":"AnimSequence","Load_Count":5,"Load_TimeSec":0.000162,"Load_SizeMB":0.010886,"Build_Count":0,"Build_TimeSec":0.0,"Build_SizeMB":0.0,"Total_Count":5,"Total_TimeSec":0.000162,"Total_SizeMB":0,"Efficiency":1.0,"Thread_TimeSec":0.0}
{"EventName":"Core.DDC.Resource","TimestampUTC":1730546289.348000,"RecordId":66,"ProjectName":"Kukoverova_Veronika","ProjectID":"00000000000000000000000000000000","Session_ID":"{46A4D377-43C5-81E5-72CD-958C72118432}","Session_Label":"","Session_StartUTC":1730546273.763,"Build_Configuration":"Development","Build_IsInternalBuild":false,"Build_IsPerforceBuild":false,"Build_IsPromotedBuild":true,"Build_BranchName":"++ue5+release-5.4","Build_Changelist":35576357,"Hardware_Platform":"Windows","Hardware_GPU":"","Hardware_CPU":"Intel(R) Core(TM) i5-10400 CPU @ 2.90GHz","Hardware_CPU_Cores_Physical":6,"Hardware_CPU_Cores_Logical":12,"Hardware_RAM":17044029440,"Hardware_ComputerName":"K411","Config_IsEditor":true,"Config_IsUnattended":false,"Config_IsBuildMachine":false,"Config_IsRunningCommandlet":false,"Config_IsDebuggerPresent":false,"SchemaVersion":3,"LoadingName":"Hitch","AssetType":"NavCollision","Load_Count":53,"Load_TimeSec":0.003395,"Load_SizeMB":0.07387,"Build_Count":0,"Build_TimeSec":0.0,"Build_SizeMB":0.0,"Total_Count":53,"Total_TimeSec":0.003395,"Total_SizeMB":0,"Efficiency":1.0,"Thread_TimeSec":0.00191}
{"EventName":"Core.DDC.Resource","TimestampUTC":1730546289.381000,"RecordId":67,"ProjectName":"Kukoverova_Veronika","ProjectID":"00000000000000000000000000000000","Session_ID":"{46A4D377-43C5-81E5-72CD-958C72118432}","Session_Label":"","Session_StartUTC":1730546273.763,"Build_Configuration":"Development","Build_IsInternalBuild":false,"Build_IsPerforceBuild":false,"Build_IsPromotedBuild":true,"Build_BranchName":"++ue5+release-5.4","Build_Changelist":35576357,"Hardware_Platform":"Windows","Hardware_GPU":"","Hardware_CPU":"Intel(R) Core(TM) i5-10400 CPU @ 2.90GHz","Hardware_CPU_Cores_Physical":6,"Hardware_CPU_Cores_Logical":12,"Hardware_RAM":17044029440,"Hardware_ComputerName":"K411","Config_IsEditor":true,"Config_IsUnattended":false,"Config_IsBuildMachine":false,"Config_IsRunningCommandlet":false,"Config_IsDebuggerPresent":false,"SchemaVersion":3,"LoadingName":"Hitch","AssetType":"Total","Load_Count":796,"Load_TimeSec":0.227969,"Load_SizeMB":228.702232,"Build_Count":0,"Build_TimeSec":0.0,"Build_SizeMB":0.0,"Total_Count":796,"Total_TimeSec":0.227969,"Total_SizeMB":228,"Efficiency":1.0,"Thread_TimeSec":0.16342}
{"EventName":"Core.DDC.Summary","TimestampUTC":1730546289.502000,"RecordId":68,"ProjectName":"Kukoverova_Veronika","ProjectID":"00000000000000000000000000000000","Session_ID":"{46A4D377-43C5-81E5-72CD-958C72118432}","Session_Label":"","Session_StartUTC":1730546273.763,"Build_Configuration":"Development","Build_IsInternalBuild":false,"Build_IsPerforceBuild":false,"Build_IsPromotedBuild":true,"Build_BranchName":"++ue5+release-5.4","Build_Changelist":35576357,"Hardware_Platform":"Windows","Hardware_GPU":"","Hardware_CPU":"Intel(R) Core(TM) i5-10400 CPU @ 2.90GHz","Hardware_CPU_Cores_Physical":6,"Hardware_CPU_Cores_Logical":12,"Hardware_RAM":17044029440,"Hardware_ComputerName":"K411","Config_IsEditor":true,"Config_IsUnattended":false,"Config_IsBuildMachine":false,"Config_IsRunningCommandlet":false,"Config_IsDebuggerPresent":false,"SchemaVersion":3,"LoadingName":"Hitch","BackEnd":"InstalledDerivedDataBackendGraph","HasLocalCache":"true","HasSharedCache":"false","HasCloudCache":"false","HasZenCache":"true","TotalGetHits":1306.0,"TotalGetMisses":57.0,"TotalGets":1363.0,"TotalGetHitPct":0.95818,"GetMissPct":0.04182,"TotalPutHits":51.0,"TotalPutMisses":0.0,"TotalPuts":51.0,"TotalPutHitPct":1.0,"PutMissPct":0.0,"LocalGetHits":0.0,"LocalGetTotal":0.0,"LocalGetHitPct":0.0,"SharedGetHits":0.0,"SharedGetTotal":0.0,"SharedGetHitPct":0.0,"ZenLocalGetHits":505.0,"ZenLocalGetTotal":562.0,"ZenLocalGetHitPct":0.898577,"ZenRemoteGetHits":0.0,"ZenRemoteGetTotal":0.0,"ZenRemoteGetHitPct":0.0,"CloudGetHits":0.0,"CloudGetTotal":0.0,"CloudGetHitPct":0.0,"LocalLatency":0.0,"LocalReadSpeed":0.0,"LocalWriteSpeed":0.0,"SharedLatency":0.0,"SharedReadSpeed":0.0,"SharedWriteSpeed":0.0,"CloudLatency":0.0,"CloudReadSpeed":0.0,"CloudWriteSpeed":0.0}
{"EventName":"Core.Zen","TimestampUTC":1730546289.536000,"RecordId":69,"ProjectName":"Kukoverova_Veronika","ProjectID":"00000000000000000000000000000000","Session_ID":"{46A4D377-43C5-81E5-72CD-958C72118432}","Session_Label":"","Session_StartUTC":1730546273.763,"Build_Configuration":"Development","Build_IsInternalBuild":false,"Build_IsPerforceBuild":false,"Build_IsPromotedBuild":true,"Build_BranchName":"++ue5+release-5.4","Build_Changelist":35576357,"Hardware_Platform":"Windows","Hardware_GPU":"","Hardware_CPU":"Intel(R) Core(TM) i5-10400 CPU @ 2.90GHz","Hardware_CPU_Cores_Physical":6,"Hardware_CPU_Cores_Logical":12,"Hardware_RAM":17044029440,"Hardware_ComputerName":"K411","Config_IsEditor":true,"Config_IsUnattended":false,"Config_IsBuildMachine":false,"Config_IsRunningCommandlet":false,"Config_IsDebuggerPresent":false,"SchemaVersion":1,"LoadingName":"Hitch","Zen_Enabled":true,"Zen_Cache_Size_Disk":168329229.0,"Zen_Cache_Size_Memory":70008.0,"Zen_Cache_Hits":459,"Zen_Cache_Misses":6,"Zen_Cache_Writes":51,"Zen_Cache_HitRatio":0.987097,"Zen_Cache_Cas_Hits":600,"Zen_Cache_Cas_Misses":0,"Zen_Cache_Cas_Writes":0,"Zen_Cache_Requests":500,"Zen_Cache_BadRequests":0,"Zen_Cache_Requests_Count":500,"Zen_Cache_Requests_RateMean":44.933583,"Zen_Cache_Requests_TAverage":0.000051,"Zen_Cache_Requests_TMin":0.000013,"Zen_Cache_Requests_TMax":0.000527,"Zen_Cache_TotalUploadedMB":0.0,"Zen_Upstream_TotalDownloadedMB":0.0,"Zen_Upstream_TotalUploadedMB":0.0,"Zen_Upstream_Requests_Count":0,"Zen_Upstream_Requests_RateMean":0.0,"Zen_Upstream_Requests_TAverage":0.0,"Zen_Upstream_Requests_TMin":0.0,"Zen_Upstream_Requests_TMax":0.0,"Zen_Cas_Size_Large":0,"Zen_Cas_Size_Small":182141384,"Zen_Cas_Size_Tiny":132153,"Zen_Cas_Size_Total":182273537,"Zen_Project_Size_Disk":0.0,"Zen_Project_Size_Memory":0.0,"Zen_Project_WriteCount":0,"Zen_Project_ReadCount":0,"Zen_Project_DeleteCount":0,"Zen_Project_Oplog_WriteCount":0,"Zen_Project_Oplog_ReadCount":0,"Zen_Project_Oplog_DeleteCount":0,"Zen_Project_Op_Hits":0,"Zen_Project_Op_Misses":0,"Zen_Project_Op_Writes":0,"Zen_Project_Chunk_Hits":0,"Zen_Project_Chunk_Misses":0,"Zen_Project_Chunk_Writes":0,"Zen_Project_Requests":0,"Zen_Project_BadRequests":0,"Zen_Project_Op_HitRatio":0.0,"Zen_Project_Chunk_HitRatio":0.0}
{"EventName":"Span","TimestampUTC":1730546289.757000,"RecordId":70,"ProjectName":"Kukoverova_Veronika","ProjectID":"00000000000000000000000000000000","Session_ID":"{46A4D377-43C5-81E5-72CD-958C72118432}","Session_Label":"","Session_StartUTC":1730546273.763,"Build_Configuration":"Development","Build_IsInternalBuild":false,"Build_IsPerforceBuild":false,"Build_IsPromotedBuild":true,"Build_BranchName":"++ue5+release-5.4","Build_Changelist":35576357,"Hardware_Platform":"Windows","Hardware_GPU":"","Hardware_CPU":"Intel(R) Core(TM) i5-10400 CPU @ 2.90GHz","Hardware_CPU_Cores_Physical":6,"Hardware_CPU_Cores_Logical":12,"Hardware_RAM":17044029440,"Hardware_ComputerName":"K411","Config_IsEditor":true,"Config_IsUnattended":false,"Config_IsBuildMachine":false,"Config_IsRunningCommandlet":false,"Config_IsDebuggerPresent":false,"SchemaVersion":1,"Span_Name":"Session","Span_GUID":"9CC3960C4205342954698993982A701D","Span_ParentName":"","Span_ThreadId":10688,"Span_Depth":0,"Span_StartUTC":1730546273.971,"Span_EndUTC":1730546289.757,"Span_TimeInSec":15.786}
{"EventName":"Span","TimestampUTC":1730546289.792000,"RecordId":71,"ProjectName":"Kukoverova_Veronika","ProjectID":"00000000000000000000000000000000","Session_ID":"{46A4D377-43C5-81E5-72CD-958C72118432}","Session_Label":"","Session_StartUTC":1730546273.763,"Build_Configuration":"Development","Build_IsInternalBuild":false,"Build_IsPerforceBuild":false,"Build_IsPromotedBuild":true,"Build_BranchName":"++ue5+release-5.4","Build_Changelist":35576357,"Hardware_Platform":"Windows","Hardware_GPU":"","Hardware_CPU":"Intel(R) Core(TM) i5-10400 CPU @ 2.90GHz","Hardware_CPU_Cores_Physical":6,"Hardware_CPU_Cores_Logical":12,"Hardware_RAM":17044029440,"Hardware_ComputerName":"K411","Config_IsEditor":true,"Config_IsUnattended":false,"Config_IsBuildMachine":false,"Config_IsRunningCommandlet":false,"Config_IsDebuggerPresent":false,"MapName":"VRTemplateMap","SchemaVersion":1,"Span_Name":"Editor","Span_GUID":"5592B3384273058C97558A927B2BA92F","Span_ParentName":"Session","Span_ThreadId":10688,"Span_Depth":1,"Span_StartUTC":1730546273.971,"Span_EndUTC":1730546289.792,"Span_TimeInSec":15.821}
{"EventName":"Span","TimestampUTC":1730546289.837000,"RecordId":72,"ProjectName":"Kukoverova_Veronika","ProjectID":"00000000000000000000000000000000","Session_ID":"{46A4D377-43C5-81E5-72CD-958C72118432}","Session_Label":"","Session_StartUTC":1730546273.763,"Build_Configuration":"Development","Build_IsInternalBuild":false,"Build_IsPerforceBuild":false,"Build_IsPromotedBuild":true,"Build_BranchName":"++ue5+release-5.4","Build_Changelist":35576357,"Hardware_Platform":"Windows","Hardware_GPU":"","Hardware_CPU":"Intel(R) Core(TM) i5-10400 CPU @ 2.90GHz","Hardware_CPU_Cores_Physical":6,"Hardware_CPU_Cores_Logical":12,"Hardware_RAM":17044029440,"Hardware_ComputerName":"K411","Config_IsEditor":true,"Config_IsUnattended":false,"Config_IsBuildMachine":false,"Config_IsRunningCommandlet":false,"Config_IsDebuggerPresent":false,"MapName":"VRTemplateMap","SchemaVersion":1,"Span_Name":"Editor.Interact","Span_GUID":"FE11949A4D957536FFAFF59A1116BA81","Span_ParentName":"Editor","Span_ThreadId":10688,"Span_Depth":2,"Span_StartUTC":1730546285.948,"Span_EndUTC":1730546289.837,"Span_TimeInSec":3.889}
{"EventName":"Span","TimestampUTC":1730546289.881000,"RecordId":73,"ProjectName":"Kukoverova_Veronika","ProjectID":"00000000000000000000000000000000","Session_ID":"{46A4D377-43C5-81E5-72CD-958C72118432}","Session_Label":"","Session_StartUTC":1730546273.763,"Build_Configuration":"Development","Build_IsInternalBuild":false,"Build_IsPerforceBuild":false,"Build_IsPromotedBuild":true,"Build_BranchName":"++ue5+release-5.4","Build_Changelist":35576357,"Hardware_Platform":"Windows","Hardware_GPU":"","Hardware_CPU":"Intel(R) Core(TM) i5-10400 CPU @ 2.90GHz","Hardware_CPU_Cores_Physical":6,"Hardware_CPU_Cores_Logical":12,"Hardware_RAM":17044029440,"Hardware_ComputerName":"K411","Config_IsEditor":true,"Config_IsUnattended":false,"Config_IsBuildMachine":false,"Config_IsRunningCommandlet":false,"Config_IsDebuggerPresent":false,"MapName":"VRTemplateMap","SchemaVersion":1,"Span_Name":"Hitching","Span_GUID":"F33B31A4438FD4CD148E6798E53E8EB4","Span_ParentName":"Editor.Interact","Span_ThreadId":10688,"Span_Depth":3,"Span_StartUTC":1730546289.709,"Span_EndUTC":1730546289.881,"Span_TimeInSec":0.172}
{"EventName":"EndSession","TimestampUTC":1730546289.925000,"RecordId":74,"ProjectName":"Kukoverova_Veronika","ProjectID":"00000000000000000000000000000000","Session_ID":"{46A4D377-43C5-81E5-72CD-958C72118432}","Session_Label":"","Session_StartUTC":1730546273.763,"Build_Configuration":"Development","Build_IsInternalBuild":false,"Build_IsPerforceBuild":false,"Build_IsPromotedBuild":true,"Build_BranchName":"++ue5+release-5.4","Build_Changelist":35576357,"Hardware_Platform":"Windows","Hardware_GPU":"","Hardware_CPU":"Intel(R) Core(TM) i5-10400 CPU @ 2.90GHz","Hardware_CPU_Cores_Physical":6,"Hardware_CPU_Cores_Logical":12,"Hardware_RAM":17044029440,"Hardware_ComputerName":"K411","Config_IsEditor":true,"Config_IsUnattended":false,"Config_IsBuildMachine":false,"Config_IsRunningCommandlet":false,"Config_IsDebuggerPresent":false}
